[
  {
    "id": 513,
    "title": "听到涛声",
    "platform": "TV",
    "onair_date": "1993-05-05",
    "rating": {
      "score": 7.8,
      "rank": 406
    },
    "poster": "https://lain.bgm.tv/pic/cover/l/3d/c4/513_Any5s.jpg",
    "images": [
      {
        "provider": "bgm",
        "quality": "large",
        "src": "https://lain.bgm.tv/pic/cover/l/3d/c4/513_Any5s.jpg"
      },
      {
        "provider": "bgm",
        "quality": "common",
        "src": "https://lain.bgm.tv/r/400/pic/cover/l/3d/c4/513_Any5s.jpg"
      },
      {
        "provider": "bgm",
        "quality": "medium",
        "src": "https://lain.bgm.tv/r/800/pic/cover/l/3d/c4/513_Any5s.jpg"
      },
      {
        "provider": "bgm",
        "quality": "small",
        "src": "https://lain.bgm.tv/r/200/pic/cover/l/3d/c4/513_Any5s.jpg"
      },
      {
        "provider": "bgm",
        "quality": "grid",
        "src": "https://lain.bgm.tv/r/100/pic/cover/l/3d/c4/513_Any5s.jpg"
      }
    ],
    "summary": "考上东京私立大学的杜崎拓，在大学生活的第一个暑假，于月台上见到一名很像高中同学武藤里伽子的女孩。之后为了参加同学会，在回到故乡高知的路上，拓想起了高中时代的回忆。与转学生里伽子的相遇、夏威夷的毕业旅行、与里伽子两人的东京之旅、和友人争执因而闹翻的文化祭。随着这些略带苦涩的记忆，拓开始回顾起里伽子的存在。",
    "alias": [
      "Ocean Waves",
      "Umi ga Kikoeru",
      "听到涛声",
      "听见涛声",
      "海がきこえる",
      "海潮之声",
      "海潮之聲"
    ],
    "tags": [
      "1990s",
      "1993年5月",
      "90年代",
      "GHIBLI",
      "TV",
      "TVSP",
      "スタジオジブリ",
      "丹羽圭子",
      "剧场版",
      "动画电影",
      "吉卜力",
      "听到涛声",
      "听见涛声",
      "宫崎骏",
      "小说改",
      "少男少女",
      "恋爱",
      "望月智充",
      "校园",
      "氷室冴子",
      "永田茂",
      "爱情",
      "电影",
      "轻改",
      "近藤胜也",
      "青春"
    ],
    "search": {
      "include": [
        "Ocean Waves",
        "Umi ga Kikoeru",
        "听到涛声",
        "听见涛声",
        "海がきこえる",
        "海潮之声",
        "海潮之聲"
      ]
    }
  },
  {
    "id": 93047,
    "title": "魔法公主明琪桃子 通往梦想之桥",
    "platform": "OVA",
    "onair_date": "1993-05-21",
    "rating": {
      "score": 6.9,
      "rank": 0
    },
    "poster": "https://lain.bgm.tv/pic/cover/l/86/58/93047_Jj2bz.jpg",
    "images": [
      {
        "provider": "bgm",
        "quality": "large",
        "src": "https://lain.bgm.tv/pic/cover/l/86/58/93047_Jj2bz.jpg"
      },
      {
        "provider": "bgm",
        "quality": "common",
        "src": "https://lain.bgm.tv/r/400/pic/cover/l/86/58/93047_Jj2bz.jpg"
      },
      {
        "provider": "bgm",
        "quality": "medium",
        "src": "https://lain.bgm.tv/r/800/pic/cover/l/86/58/93047_Jj2bz.jpg"
      },
      {
        "provider": "bgm",
        "quality": "small",
        "src": "https://lain.bgm.tv/r/200/pic/cover/l/86/58/93047_Jj2bz.jpg"
      },
      {
        "provider": "bgm",
        "quality": "grid",
        "src": "https://lain.bgm.tv/r/100/pic/cover/l/86/58/93047_Jj2bz.jpg"
      }
    ],
    "summary": "「この橋で出会った者は別れ別れになっても再び会える」という言い伝えがある橋の上で、モモは一人の少年と出会う。少年は橋の言い伝えを信じ誰かを待っていたが、待ち人に会えずあきらめかけていた。モモは言い伝えが本当だと証明するために、少年と再会の約束をする。\nそれから、モモは約束を果たすため橋に通い続ける。季節が移りゆく中、少年を待ち続けるモモは橋の上で起きる出会いと別れを見つめ続けていく。",
    "alias": [
      "MINKY MOMO IN 夢にかける橋",
      "魔法公主明琪桃子 通往梦想之桥"
    ],
    "tags": [
      "1993年5月",
      "OVA",
      "原创",
      "汤山邦彦",
      "首藤刚志"
    ],
    "search": {
      "include": [
        "MINKY MOMO IN 夢にかける橋",
        "魔法公主明琪桃子 通往梦想之桥"
      ]
    }
  },
  {
    "id": 315559,
    "title": "けろけろけろっぴのよわむし王子の大冒険",
    "platform": "OVA",
    "onair_date": "1993-05-21",
    "rating": {
      "score": 6,
      "rank": 0
    },
    "poster": "https://lain.bgm.tv/pic/cover/l/bd/4b/315559_wqIQQ.jpg",
    "images": [
      {
        "provider": "bgm",
        "quality": "large",
        "src": "https://lain.bgm.tv/pic/cover/l/bd/4b/315559_wqIQQ.jpg"
      },
      {
        "provider": "bgm",
        "quality": "common",
        "src": "https://lain.bgm.tv/r/400/pic/cover/l/bd/4b/315559_wqIQQ.jpg"
      },
      {
        "provider": "bgm",
        "quality": "medium",
        "src": "https://lain.bgm.tv/r/800/pic/cover/l/bd/4b/315559_wqIQQ.jpg"
      },
      {
        "provider": "bgm",
        "quality": "small",
        "src": "https://lain.bgm.tv/r/200/pic/cover/l/bd/4b/315559_wqIQQ.jpg"
      },
      {
        "provider": "bgm",
        "quality": "grid",
        "src": "https://lain.bgm.tv/r/100/pic/cover/l/bd/4b/315559_wqIQQ.jpg"
      }
    ],
    "summary": "七つの世界を治めた伝説の英雄ケロン王子の映画を見に行くけろっぴたち。広場では乱暴者たちが我が物顔で振る舞っています。「ケロン王子のように強かったら…!」おじけづくけろっぴは悔しく思います。ところが映画の中の王子はまるで弱虫。場内から野次が飛び交います。王子の「助けて」の叫びに応えたいけろっぴ。その時不思議なことが!!なんとけろっぴが映画の中に入ってしまったのです。勇者の剣をめざして二人の大冒険が始まります。",
    "alias": [
      "Kero Kero Keroppi no Yowamushi-ouji no Daibouken",
      "けろけろけろっぴのよわむし王子の大冒険"
    ],
    "tags": [],
    "search": {
      "include": [
        "Kero Kero Keroppi no Yowamushi-ouji no Daibouken",
        "けろけろけろっぴのよわむし王子の大冒険"
      ]
    }
  }
]