[
  {
    "id": 806,
    "data": {
      "date": "1963-01-01",
      "platform": "TV",
      "images": {
        "small": "https://lain.bgm.tv/r/200/pic/cover/l/d5/80/806_30VAB.jpg",
        "grid": "https://lain.bgm.tv/r/100/pic/cover/l/d5/80/806_30VAB.jpg",
        "large": "https://lain.bgm.tv/pic/cover/l/d5/80/806_30VAB.jpg",
        "medium": "https://lain.bgm.tv/r/800/pic/cover/l/d5/80/806_30VAB.jpg",
        "common": "https://lain.bgm.tv/r/400/pic/cover/l/d5/80/806_30VAB.jpg"
      },
      "summary": "《铁臂阿童木》（日语：鉄腕アトム，台湾译作《原子小金刚》，港澳译作《小飞侠阿童木》；港旧译《无敌小飞侠》，台湾华视别译《小战士》）是一套科幻漫画作品，也是日本漫画界一代宗师手冢治虫的首部长篇连载作品，于1952年至1968年首次于光文社的《少年》漫画杂志连载。故事讲述少年仿生人阿童木在未来21世纪里为了人类的福祉而活跃。中国大陆及香港版主角名称“阿童木”是日语“アトム”的发音直译，词语源自英语“Atom”，意即“原子”。\r\n\r\n本剧在1960年代以电视黑白动画片形式首次出现，共193集，1963年至1966年于日本富士电视台播放，并取得全日本平均30%的收视率佳绩。其后此片被译成英文版本，并销往世界各地。\r\n\r\n本剧同时亦是中国正式引进的第一部海外TV版动画片。央视周末六点半档热播。由卡西欧公司“免费赠与”，条件是捆绑播放卡西欧电子表广告。日本漫画大师手塚治虫经典作品。《铁臂阿童木》开国内引进海外动画TV版之先河，其意义早已超出了作品本身。它使中国观众大开眼界，从此，日本欧美动画作品开始源源不断进入中国大陆市场……",
      "name": "鉄腕アトム",
      "name_cn": "铁臂阿童木",
      "tags": [
        {
          "name": "童年",
          "count": 270,
          "total_cont": 0
        },
        {
          "name": "铁臂阿童木",
          "count": 243,
          "total_cont": 0
        },
        {
          "name": "手冢治虫",
          "count": 174,
          "total_cont": 0
        },
        {
          "name": "怀旧",
          "count": 153,
          "total_cont": 0
        },
        {
          "name": "科幻",
          "count": 121,
          "total_cont": 0
        },
        {
          "name": "TV",
          "count": 95,
          "total_cont": 0
        },
        {
          "name": "儿时的回忆",
          "count": 74,
          "total_cont": 0
        },
        {
          "name": "没看完",
          "count": 70,
          "total_cont": 0
        },
        {
          "name": "1963",
          "count": 57,
          "total_cont": 0
        },
        {
          "name": "手冢治虫原著",
          "count": 53,
          "total_cont": 0
        },
        {
          "name": "漫画改",
          "count": 42,
          "total_cont": 0
        },
        {
          "name": "经典",
          "count": 42,
          "total_cont": 0
        },
        {
          "name": "日本",
          "count": 31,
          "total_cont": 0
        },
        {
          "name": "童年系",
          "count": 23,
          "total_cont": 0
        },
        {
          "name": "萝卜",
          "count": 14,
          "total_cont": 0
        },
        {
          "name": "漫改",
          "count": 12,
          "total_cont": 0
        },
        {
          "name": "虫Production",
          "count": 9,
          "total_cont": 0
        },
        {
          "name": "虫プロダクション",
          "count": 8,
          "total_cont": 0
        },
        {
          "name": "手塚治虫",
          "count": 7,
          "total_cont": 0
        },
        {
          "name": "铁臂",
          "count": 5,
          "total_cont": 0
        },
        {
          "name": "60年代",
          "count": 5,
          "total_cont": 0
        },
        {
          "name": "阿木",
          "count": 5,
          "total_cont": 0
        },
        {
          "name": "动画",
          "count": 4,
          "total_cont": 0
        },
        {
          "name": "虫制作",
          "count": 3,
          "total_cont": 0
        },
        {
          "name": "60s",
          "count": 3,
          "total_cont": 0
        },
        {
          "name": "日本动画",
          "count": 3,
          "total_cont": 0
        },
        {
          "name": "长篇",
          "count": 3,
          "total_cont": 0
        },
        {
          "name": "战斗",
          "count": 3,
          "total_cont": 0
        },
        {
          "name": "动作",
          "count": 2,
          "total_cont": 0
        },
        {
          "name": "SF",
          "count": 2,
          "total_cont": 0
        }
      ],
      "infobox": [
        {
          "key": "中文名",
          "value": "铁臂阿童木"
        },
        {
          "key": "别名",
          "value": [
            {
              "v": "原子小金刚"
            },
            {
              "v": "小飛俠阿童木"
            },
            {
              "v": "无敌小飞侠"
            },
            {
              "v": "小飞侠"
            },
            {
              "v": "小战士"
            }
          ]
        },
        {
          "key": "话数",
          "value": "193"
        },
        {
          "key": "放送开始",
          "value": "1963年1月1日"
        },
        {
          "key": "播放结束",
          "value": "1966年12月31日"
        },
        {
          "key": "演出",
          "value": "石井元明、林重行（りんたろう）、白川大作、片冈忠三、柴山达雄、鈴木伸一、青木茂、坂本雄作、高木厚、泽涉、勝井千賀雄、出﨑統、北野英明、远藤政治、西牧秀雄（西牧秀夫）、大西清、岡崎稔、斋出光布、山本义也、杉山卓"
        },
        {
          "key": "脚本",
          "value": "斋出光布、能加平、柴山达雄、加藤靖三、佐胁彻、片冈忠三、坂本雄作、高木厚、石津岚、佐胁彻、\t本间文幸、山本暎一、高桥健一、新田修介、山野浩一、丰田有恒、鳥海尽三、平见修司、坂本雄作、井上、小森四郎、西牧秀雄（西牧秀夫）"
        },
        {
          "key": "制作进行",
          "value": "川畑栄一、須藤省三、高橋健一、石津嵐、上梨一也、鈴木良武、片岡忠三、柴山達雄、森柾、富野喜幸（富野由悠季）、黒川慶二朗、高橋良介"
        },
        {
          "key": "作画监督",
          "value": "内野純緒"
        },
        {
          "key": "原画",
          "value": "坂本雄作、杉井儀三郎、石井元明、山本繁、瀬山義文、北野英明、青木茂、岡迫亘弘、田中英二、赤堀幹治"
        },
        {
          "key": "补间动画",
          "value": "中村和子、山本繁、林重行"
        }
      ],
      "rating": {
        "rank": 605,
        "total": 1003,
        "count": {
          "1": 1,
          "2": 5,
          "3": 1,
          "4": 3,
          "5": 25,
          "6": 101,
          "7": 286,
          "8": 366,
          "9": 130,
          "10": 85
        },
        "score": 7.7
      },
      "total_episodes": 193,
      "collection": {
        "on_hold": 131,
        "dropped": 56,
        "wish": 220,
        "collect": 1807,
        "doing": 38
      },
      "id": 806,
      "eps": 193,
      "meta_tags": [
        "科幻",
        "TV",
        "日本",
        "漫画改"
      ],
      "volumes": 0,
      "series": false,
      "locked": false,
      "nsfw": false,
      "type": 2
    },
    "persons": [
      {
        "images": {
          "small": "https://lain.bgm.tv/r/100/pic/crt/l/0d/f3/639_prsn_wAeUL.jpg?r=1688569111",
          "grid": "https://lain.bgm.tv/pic/crt/g/0d/f3/639_prsn_wAeUL.jpg?r=1688569111",
          "large": "https://lain.bgm.tv/pic/crt/l/0d/f3/639_prsn_wAeUL.jpg?r=1688569111",
          "medium": "https://lain.bgm.tv/r/400/pic/crt/l/0d/f3/639_prsn_wAeUL.jpg?r=1688569111"
        },
        "name": "高橋良輔",
        "relation": "演出助理",
        "career": [
          "producer"
        ],
        "type": 1,
        "id": 639,
        "eps": ""
      },
      {
        "images": {
          "small": "https://lain.bgm.tv/r/100/pic/crt/l/86/08/613_prsn_jZVU6.jpg",
          "grid": "https://lain.bgm.tv/pic/crt/g/86/08/613_prsn_jZVU6.jpg",
          "large": "https://lain.bgm.tv/pic/crt/l/86/08/613_prsn_jZVU6.jpg",
          "medium": "https://lain.bgm.tv/r/400/pic/crt/l/86/08/613_prsn_jZVU6.jpg"
        },
        "name": "富野由悠季",
        "relation": "演出助理",
        "career": [
          "producer"
        ],
        "type": 1,
        "id": 613,
        "eps": ""
      },
      {
        "images": {
          "small": "https://lain.bgm.tv/r/100/pic/crt/l/cb/99/2196_prsn_Pmm63.jpg?r=1717493237",
          "grid": "https://lain.bgm.tv/pic/crt/g/cb/99/2196_prsn_Pmm63.jpg?r=1717493237",
          "large": "https://lain.bgm.tv/pic/crt/l/cb/99/2196_prsn_Pmm63.jpg?r=1717493237",
          "medium": "https://lain.bgm.tv/r/400/pic/crt/l/cb/99/2196_prsn_Pmm63.jpg?r=1717493237"
        },
        "name": "山浦栄二",
        "relation": "摄影",
        "career": [
          "producer"
        ],
        "type": 1,
        "id": 2196,
        "eps": ""
      },
      {
        "images": {
          "small": "https://lain.bgm.tv/r/100/pic/crt/l/77/9e/2959_prsn_anidb.jpg",
          "grid": "https://lain.bgm.tv/pic/crt/g/77/9e/2959_prsn_anidb.jpg",
          "large": "https://lain.bgm.tv/pic/crt/l/77/9e/2959_prsn_anidb.jpg",
          "medium": "https://lain.bgm.tv/r/400/pic/crt/l/77/9e/2959_prsn_anidb.jpg"
        },
        "name": "虫プロダクション",
        "relation": "动画制作",
        "career": [
          "producer"
        ],
        "type": 2,
        "id": 2959,
        "eps": ""
      },
      {
        "images": {
          "small": "https://lain.bgm.tv/r/100/pic/crt/l/86/08/613_prsn_jZVU6.jpg",
          "grid": "https://lain.bgm.tv/pic/crt/g/86/08/613_prsn_jZVU6.jpg",
          "large": "https://lain.bgm.tv/pic/crt/l/86/08/613_prsn_jZVU6.jpg",
          "medium": "https://lain.bgm.tv/r/400/pic/crt/l/86/08/613_prsn_jZVU6.jpg"
        },
        "name": "富野由悠季",
        "relation": "制作进行",
        "career": [
          "producer"
        ],
        "type": 1,
        "id": 613,
        "eps": ""
      },
      {
        "images": {
          "small": "https://lain.bgm.tv/r/100/pic/crt/l/0d/f3/639_prsn_wAeUL.jpg?r=1688569111",
          "grid": "https://lain.bgm.tv/pic/crt/g/0d/f3/639_prsn_wAeUL.jpg?r=1688569111",
          "large": "https://lain.bgm.tv/pic/crt/l/0d/f3/639_prsn_wAeUL.jpg?r=1688569111",
          "medium": "https://lain.bgm.tv/r/400/pic/crt/l/0d/f3/639_prsn_wAeUL.jpg?r=1688569111"
        },
        "name": "高橋良輔",
        "relation": "制作进行",
        "career": [
          "producer"
        ],
        "type": 1,
        "id": 639,
        "eps": ""
      },
      {
        "images": {
          "small": "https://lain.bgm.tv/r/100/pic/crt/l/ae/ef/64647_prsn_IA0Iq.jpg",
          "grid": "https://lain.bgm.tv/pic/crt/g/ae/ef/64647_prsn_IA0Iq.jpg",
          "large": "https://lain.bgm.tv/pic/crt/l/ae/ef/64647_prsn_IA0Iq.jpg",
          "medium": "https://lain.bgm.tv/r/400/pic/crt/l/ae/ef/64647_prsn_IA0Iq.jpg"
        },
        "name": "瀬山義文",
        "relation": "补间动画",
        "career": [
          "producer"
        ],
        "type": 1,
        "id": 64647,
        "eps": ""
      },
      {
        "images": {
          "small": "https://lain.bgm.tv/r/100/pic/crt/l/2b/3b/1513_prsn_anidb.jpg?r=1489325177",
          "grid": "https://lain.bgm.tv/pic/crt/g/2b/3b/1513_prsn_anidb.jpg?r=1489325177",
          "large": "https://lain.bgm.tv/pic/crt/l/2b/3b/1513_prsn_anidb.jpg?r=1489325177",
          "medium": "https://lain.bgm.tv/r/400/pic/crt/l/2b/3b/1513_prsn_anidb.jpg?r=1489325177"
        },
        "name": "出﨑統",
        "relation": "补间动画",
        "career": [
          "producer",
          "mangaka"
        ],
        "type": 1,
        "id": 1513,
        "eps": ""
      },
      {
        "images": {
          "small": "https://lain.bgm.tv/r/100/pic/crt/l/a6/b3/2951_prsn_2fYG2.jpg",
          "grid": "https://lain.bgm.tv/pic/crt/g/a6/b3/2951_prsn_2fYG2.jpg",
          "large": "https://lain.bgm.tv/pic/crt/l/a6/b3/2951_prsn_2fYG2.jpg",
          "medium": "https://lain.bgm.tv/r/400/pic/crt/l/a6/b3/2951_prsn_2fYG2.jpg"
        },
        "name": "大橋学",
        "relation": "补间动画",
        "career": [
          "producer"
        ],
        "type": 1,
        "id": 2951,
        "eps": ""
      },
      {
        "images": {
          "small": "https://lain.bgm.tv/r/100/pic/crt/l/2f/96/1553_prsn_ffURB.jpg",
          "grid": "https://lain.bgm.tv/pic/crt/g/2f/96/1553_prsn_ffURB.jpg",
          "large": "https://lain.bgm.tv/pic/crt/l/2f/96/1553_prsn_ffURB.jpg",
          "medium": "https://lain.bgm.tv/r/400/pic/crt/l/2f/96/1553_prsn_ffURB.jpg"
        },
        "name": "杉野昭夫",
        "relation": "补间动画",
        "career": [
          "producer"
        ],
        "type": 1,
        "id": 1553,
        "eps": ""
      },
      {
        "images": {
          "small": "https://lain.bgm.tv/r/100/pic/crt/l/d9/39/13106_prsn_MQScS.jpg",
          "grid": "https://lain.bgm.tv/pic/crt/g/d9/39/13106_prsn_MQScS.jpg",
          "large": "https://lain.bgm.tv/pic/crt/l/d9/39/13106_prsn_MQScS.jpg",
          "medium": "https://lain.bgm.tv/r/400/pic/crt/l/d9/39/13106_prsn_MQScS.jpg"
        },
        "name": "椋尾篁",
        "relation": "背景美术",
        "career": [
          "producer"
        ],
        "type": 1,
        "id": 13106,
        "eps": ""
      },
      {
        "images": {
          "small": "https://lain.bgm.tv/r/100/pic/crt/l/f9/56/64656_prsn_U992O.jpg",
          "grid": "https://lain.bgm.tv/pic/crt/g/f9/56/64656_prsn_U992O.jpg",
          "large": "https://lain.bgm.tv/pic/crt/l/f9/56/64656_prsn_U992O.jpg",
          "medium": "https://lain.bgm.tv/r/400/pic/crt/l/f9/56/64656_prsn_U992O.jpg"
        },
        "name": "鈴木森繁",
        "relation": "背景美术",
        "career": [
          "producer"
        ],
        "type": 2,
        "id": 64656,
        "eps": ""
      },
      {
        "images": {
          "small": "https://lain.bgm.tv/r/100/pic/crt/l/ae/ef/64647_prsn_IA0Iq.jpg",
          "grid": "https://lain.bgm.tv/pic/crt/g/ae/ef/64647_prsn_IA0Iq.jpg",
          "large": "https://lain.bgm.tv/pic/crt/l/ae/ef/64647_prsn_IA0Iq.jpg",
          "medium": "https://lain.bgm.tv/r/400/pic/crt/l/ae/ef/64647_prsn_IA0Iq.jpg"
        },
        "name": "瀬山義文",
        "relation": "第二原画",
        "career": [
          "producer"
        ],
        "type": 1,
        "id": 64647,
        "eps": ""
      },
      {
        "images": {
          "small": "https://lain.bgm.tv/r/100/pic/crt/l/29/95/1772_prsn_anidb.jpg",
          "grid": "https://lain.bgm.tv/pic/crt/g/29/95/1772_prsn_anidb.jpg",
          "large": "https://lain.bgm.tv/pic/crt/l/29/95/1772_prsn_anidb.jpg",
          "medium": "https://lain.bgm.tv/r/400/pic/crt/l/29/95/1772_prsn_anidb.jpg"
        },
        "name": "吉川惣司",
        "relation": "原画",
        "career": [
          "producer"
        ],
        "type": 1,
        "id": 1772,
        "eps": ""
      },
      {
        "images": {
          "small": "",
          "grid": "",
          "large": "",
          "medium": ""
        },
        "name": "村野守美",
        "relation": "原画",
        "career": [
          "producer"
        ],
        "type": 1,
        "id": 2345,
        "eps": ""
      },
      {
        "images": {
          "small": "https://lain.bgm.tv/r/100/pic/crt/l/2b/3b/1513_prsn_anidb.jpg?r=1489325177",
          "grid": "https://lain.bgm.tv/pic/crt/g/2b/3b/1513_prsn_anidb.jpg?r=1489325177",
          "large": "https://lain.bgm.tv/pic/crt/l/2b/3b/1513_prsn_anidb.jpg?r=1489325177",
          "medium": "https://lain.bgm.tv/r/400/pic/crt/l/2b/3b/1513_prsn_anidb.jpg?r=1489325177"
        },
        "name": "出﨑統",
        "relation": "原画",
        "career": [
          "producer",
          "mangaka"
        ],
        "type": 1,
        "id": 1513,
        "eps": ""
      },
      {
        "images": {
          "small": "",
          "grid": "",
          "large": "",
          "medium": ""
        },
        "name": "正延宏三",
        "relation": "原画",
        "career": [
          "producer"
        ],
        "type": 1,
        "id": 11626,
        "eps": ""
      },
      {
        "images": {
          "small": "",
          "grid": "",
          "large": "",
          "medium": ""
        },
        "name": "紺野修司",
        "relation": "原画",
        "career": [
          "producer"
        ],
        "type": 1,
        "id": 27219,
        "eps": ""
      },
      {
        "images": {
          "small": "https://lain.bgm.tv/r/100/pic/crt/l/2f/96/1553_prsn_ffURB.jpg",
          "grid": "https://lain.bgm.tv/pic/crt/g/2f/96/1553_prsn_ffURB.jpg",
          "large": "https://lain.bgm.tv/pic/crt/l/2f/96/1553_prsn_ffURB.jpg",
          "medium": "https://lain.bgm.tv/r/400/pic/crt/l/2f/96/1553_prsn_ffURB.jpg"
        },
        "name": "杉野昭夫",
        "relation": "原画",
        "career": [
          "producer"
        ],
        "type": 1,
        "id": 1553,
        "eps": ""
      },
      {
        "images": {
          "small": "https://lain.bgm.tv/r/100/pic/crt/l/bf/fc/1483_prsn_anidb.jpg",
          "grid": "https://lain.bgm.tv/pic/crt/g/bf/fc/1483_prsn_anidb.jpg",
          "large": "https://lain.bgm.tv/pic/crt/l/bf/fc/1483_prsn_anidb.jpg",
          "medium": "https://lain.bgm.tv/r/400/pic/crt/l/bf/fc/1483_prsn_anidb.jpg"
        },
        "name": "石黒昇",
        "relation": "原画",
        "career": [
          "producer"
        ],
        "type": 1,
        "id": 1483,
        "eps": ""
      },
      {
        "images": {
          "small": "https://lain.bgm.tv/r/100/pic/crt/l/ae/ef/64647_prsn_IA0Iq.jpg",
          "grid": "https://lain.bgm.tv/pic/crt/g/ae/ef/64647_prsn_IA0Iq.jpg",
          "large": "https://lain.bgm.tv/pic/crt/l/ae/ef/64647_prsn_IA0Iq.jpg",
          "medium": "https://lain.bgm.tv/r/400/pic/crt/l/ae/ef/64647_prsn_IA0Iq.jpg"
        },
        "name": "瀬山義文",
        "relation": "原画",
        "career": [
          "producer"
        ],
        "type": 1,
        "id": 64647,
        "eps": ""
      },
      {
        "images": {
          "small": "https://lain.bgm.tv/r/100/pic/crt/l/2b/3b/1513_prsn_anidb.jpg?r=1489325177",
          "grid": "https://lain.bgm.tv/pic/crt/g/2b/3b/1513_prsn_anidb.jpg?r=1489325177",
          "large": "https://lain.bgm.tv/pic/crt/l/2b/3b/1513_prsn_anidb.jpg?r=1489325177",
          "medium": "https://lain.bgm.tv/r/400/pic/crt/l/2b/3b/1513_prsn_anidb.jpg?r=1489325177"
        },
        "name": "出﨑統",
        "relation": "作画监督",
        "career": [
          "producer",
          "mangaka"
        ],
        "type": 1,
        "id": 1513,
        "eps": ""
      },
      {
        "images": {
          "small": "https://lain.bgm.tv/r/100/pic/crt/l/09/dd/2832_prsn_RQFwZ.jpg",
          "grid": "https://lain.bgm.tv/pic/crt/g/09/dd/2832_prsn_RQFwZ.jpg",
          "large": "https://lain.bgm.tv/pic/crt/l/09/dd/2832_prsn_RQFwZ.jpg",
          "medium": "https://lain.bgm.tv/r/400/pic/crt/l/09/dd/2832_prsn_RQFwZ.jpg"
        },
        "name": "勝井千賀雄",
        "relation": "演出",
        "career": [
          "producer"
        ],
        "type": 1,
        "id": 2832,
        "eps": ""
      },
      {
        "images": {
          "small": "https://lain.bgm.tv/r/100/pic/crt/l/76/cf/1318_prsn_anidb.jpg",
          "grid": "https://lain.bgm.tv/pic/crt/g/76/cf/1318_prsn_anidb.jpg",
          "large": "https://lain.bgm.tv/pic/crt/l/76/cf/1318_prsn_anidb.jpg",
          "medium": "https://lain.bgm.tv/r/400/pic/crt/l/76/cf/1318_prsn_anidb.jpg"
        },
        "name": "手塚治虫",
        "relation": "演出",
        "career": [
          "producer",
          "mangaka"
        ],
        "type": 1,
        "id": 1318,
        "eps": ""
      },
      {
        "images": {
          "small": "https://lain.bgm.tv/r/100/pic/crt/l/6a/4c/2487_prsn_anidb.jpg",
          "grid": "https://lain.bgm.tv/pic/crt/g/6a/4c/2487_prsn_anidb.jpg",
          "large": "https://lain.bgm.tv/pic/crt/l/6a/4c/2487_prsn_anidb.jpg",
          "medium": "https://lain.bgm.tv/r/400/pic/crt/l/6a/4c/2487_prsn_anidb.jpg"
        },
        "name": "白川大作",
        "relation": "演出",
        "career": [
          "producer"
        ],
        "type": 1,
        "id": 2487,
        "eps": ""
      },
      {
        "images": {
          "small": "",
          "grid": "",
          "large": "",
          "medium": ""
        },
        "name": "永樹凡人",
        "relation": "演出",
        "career": [
          "producer"
        ],
        "type": 1,
        "id": 3452,
        "eps": ""
      },
      {
        "images": {
          "small": "https://lain.bgm.tv/r/100/pic/crt/l/26/99/1880_prsn_E9zEi.jpg",
          "grid": "https://lain.bgm.tv/pic/crt/g/26/99/1880_prsn_E9zEi.jpg",
          "large": "https://lain.bgm.tv/pic/crt/l/26/99/1880_prsn_E9zEi.jpg",
          "medium": "https://lain.bgm.tv/r/400/pic/crt/l/26/99/1880_prsn_E9zEi.jpg"
        },
        "name": "永島慎二",
        "relation": "演出",
        "career": [
          "producer",
          "mangaka"
        ],
        "type": 1,
        "id": 1880,
        "eps": ""
      },
      {
        "images": {
          "small": "https://lain.bgm.tv/r/100/pic/crt/l/2b/3b/1513_prsn_anidb.jpg?r=1489325177",
          "grid": "https://lain.bgm.tv/pic/crt/g/2b/3b/1513_prsn_anidb.jpg?r=1489325177",
          "large": "https://lain.bgm.tv/pic/crt/l/2b/3b/1513_prsn_anidb.jpg?r=1489325177",
          "medium": "https://lain.bgm.tv/r/400/pic/crt/l/2b/3b/1513_prsn_anidb.jpg?r=1489325177"
        },
        "name": "出﨑統",
        "relation": "演出",
        "career": [
          "producer",
          "mangaka"
        ],
        "type": 1,
        "id": 1513,
        "eps": ""
      },
      {
        "images": {
          "small": "https://lain.bgm.tv/r/100/pic/crt/l/86/08/613_prsn_jZVU6.jpg",
          "grid": "https://lain.bgm.tv/pic/crt/g/86/08/613_prsn_jZVU6.jpg",
          "large": "https://lain.bgm.tv/pic/crt/l/86/08/613_prsn_jZVU6.jpg",
          "medium": "https://lain.bgm.tv/r/400/pic/crt/l/86/08/613_prsn_jZVU6.jpg"
        },
        "name": "富野由悠季",
        "relation": "演出",
        "career": [
          "producer"
        ],
        "type": 1,
        "id": 613,
        "eps": ""
      },
      {
        "images": {
          "small": "",
          "grid": "",
          "large": "",
          "medium": ""
        },
        "name": "遠藤政治",
        "relation": "演出",
        "career": [
          "producer"
        ],
        "type": 1,
        "id": 2531,
        "eps": ""
      },
      {
        "images": {
          "small": "https://lain.bgm.tv/r/100/pic/crt/l/88/1c/2852_prsn_anidb.jpg",
          "grid": "https://lain.bgm.tv/pic/crt/g/88/1c/2852_prsn_anidb.jpg",
          "large": "https://lain.bgm.tv/pic/crt/l/88/1c/2852_prsn_anidb.jpg",
          "medium": "https://lain.bgm.tv/r/400/pic/crt/l/88/1c/2852_prsn_anidb.jpg"
        },
        "name": "鈴木伸一",
        "relation": "演出",
        "career": [
          "producer",
          "mangaka"
        ],
        "type": 1,
        "id": 2852,
        "eps": ""
      },
      {
        "images": {
          "small": "https://lain.bgm.tv/r/100/pic/crt/l/69/cd/3051_prsn_QRS2A.jpg",
          "grid": "https://lain.bgm.tv/pic/crt/g/69/cd/3051_prsn_QRS2A.jpg",
          "large": "https://lain.bgm.tv/pic/crt/l/69/cd/3051_prsn_QRS2A.jpg",
          "medium": "https://lain.bgm.tv/r/400/pic/crt/l/69/cd/3051_prsn_QRS2A.jpg"
        },
        "name": "岡崎稔",
        "relation": "演出",
        "career": [
          "producer"
        ],
        "type": 1,
        "id": 3051,
        "eps": ""
      },
      {
        "images": {
          "small": "https://lain.bgm.tv/r/100/pic/crt/l/84/0a/1957_prsn_W88ih.jpg",
          "grid": "https://lain.bgm.tv/pic/crt/g/84/0a/1957_prsn_W88ih.jpg",
          "large": "https://lain.bgm.tv/pic/crt/l/84/0a/1957_prsn_W88ih.jpg",
          "medium": "https://lain.bgm.tv/r/400/pic/crt/l/84/0a/1957_prsn_W88ih.jpg"
        },
        "name": "杉山卓",
        "relation": "演出",
        "career": [
          "producer"
        ],
        "type": 1,
        "id": 1957,
        "eps": ""
      },
      {
        "images": {
          "small": "https://lain.bgm.tv/r/100/pic/crt/l/92/1f/912_prsn_6zt9e.jpg?r=1717653895",
          "grid": "https://lain.bgm.tv/pic/crt/g/92/1f/912_prsn_6zt9e.jpg?r=1717653895",
          "large": "https://lain.bgm.tv/pic/crt/l/92/1f/912_prsn_6zt9e.jpg?r=1717653895",
          "medium": "https://lain.bgm.tv/r/400/pic/crt/l/92/1f/912_prsn_6zt9e.jpg?r=1717653895"
        },
        "name": "りんたろう",
        "relation": "演出",
        "career": [
          "producer"
        ],
        "type": 1,
        "id": 912,
        "eps": ""
      },
      {
        "images": {
          "small": "",
          "grid": "",
          "large": "",
          "medium": ""
        },
        "name": "紺野修司",
        "relation": "演出",
        "career": [
          "producer"
        ],
        "type": 1,
        "id": 27219,
        "eps": ""
      },
      {
        "images": {
          "small": "https://lain.bgm.tv/r/100/pic/crt/l/83/03/1691_prsn_anidb.jpg",
          "grid": "https://lain.bgm.tv/pic/crt/g/83/03/1691_prsn_anidb.jpg",
          "large": "https://lain.bgm.tv/pic/crt/l/83/03/1691_prsn_anidb.jpg",
          "medium": "https://lain.bgm.tv/r/400/pic/crt/l/83/03/1691_prsn_anidb.jpg"
        },
        "name": "山本暎一",
        "relation": "演出",
        "career": [
          "producer"
        ],
        "type": 1,
        "id": 1691,
        "eps": ""
      },
      {
        "images": {
          "small": "",
          "grid": "",
          "large": "",
          "medium": ""
        },
        "name": "上梨満雄",
        "relation": "演出",
        "career": [
          "producer"
        ],
        "type": 1,
        "id": 21975,
        "eps": ""
      },
      {
        "images": {
          "small": "",
          "grid": "",
          "large": "",
          "medium": ""
        },
        "name": "西牧秀夫",
        "relation": "演出",
        "career": [
          "producer"
        ],
        "type": 1,
        "id": 3801,
        "eps": ""
      },
      {
        "images": {
          "small": "https://lain.bgm.tv/r/100/pic/crt/l/e9/59/967_prsn_7VbsV.jpg",
          "grid": "https://lain.bgm.tv/pic/crt/g/e9/59/967_prsn_7VbsV.jpg",
          "large": "https://lain.bgm.tv/pic/crt/l/e9/59/967_prsn_7VbsV.jpg",
          "medium": "https://lain.bgm.tv/r/400/pic/crt/l/e9/59/967_prsn_7VbsV.jpg"
        },
        "name": "坂本雄作",
        "relation": "演出",
        "career": [
          "producer"
        ],
        "type": 1,
        "id": 967,
        "eps": ""
      },
      {
        "images": {
          "small": "https://lain.bgm.tv/r/100/pic/crt/l/6f/3e/1300_prsn_anidb.jpg",
          "grid": "https://lain.bgm.tv/pic/crt/g/6f/3e/1300_prsn_anidb.jpg",
          "large": "https://lain.bgm.tv/pic/crt/l/6f/3e/1300_prsn_anidb.jpg",
          "medium": "https://lain.bgm.tv/r/400/pic/crt/l/6f/3e/1300_prsn_anidb.jpg"
        },
        "name": "杉井ギサブロー",
        "relation": "演出",
        "career": [
          "producer"
        ],
        "type": 1,
        "id": 1300,
        "eps": ""
      },
      {
        "images": {
          "small": "https://lain.bgm.tv/r/100/pic/crt/l/90/db/1420_prsn_anidb.jpg",
          "grid": "https://lain.bgm.tv/pic/crt/g/90/db/1420_prsn_anidb.jpg",
          "large": "https://lain.bgm.tv/pic/crt/l/90/db/1420_prsn_anidb.jpg",
          "medium": "https://lain.bgm.tv/r/400/pic/crt/l/90/db/1420_prsn_anidb.jpg"
        },
        "name": "辻真先",
        "relation": "脚本",
        "career": [
          "producer"
        ],
        "type": 1,
        "id": 1420,
        "eps": ""
      },
      {
        "images": {
          "small": "https://lain.bgm.tv/r/100/pic/crt/l/76/cf/1318_prsn_anidb.jpg",
          "grid": "https://lain.bgm.tv/pic/crt/g/76/cf/1318_prsn_anidb.jpg",
          "large": "https://lain.bgm.tv/pic/crt/l/76/cf/1318_prsn_anidb.jpg",
          "medium": "https://lain.bgm.tv/r/400/pic/crt/l/76/cf/1318_prsn_anidb.jpg"
        },
        "name": "手塚治虫",
        "relation": "脚本",
        "career": [
          "producer",
          "mangaka"
        ],
        "type": 1,
        "id": 1318,
        "eps": ""
      },
      {
        "images": {
          "small": "",
          "grid": "",
          "large": "",
          "medium": ""
        },
        "name": "平見修二",
        "relation": "脚本",
        "career": [
          "producer"
        ],
        "type": 1,
        "id": 21981,
        "eps": ""
      },
      {
        "images": {
          "small": "",
          "grid": "",
          "large": "",
          "medium": ""
        },
        "name": "上梨満雄",
        "relation": "脚本",
        "career": [
          "producer"
        ],
        "type": 1,
        "id": 21975,
        "eps": ""
      },
      {
        "images": {
          "small": "https://lain.bgm.tv/r/100/pic/crt/l/86/08/613_prsn_jZVU6.jpg",
          "grid": "https://lain.bgm.tv/pic/crt/g/86/08/613_prsn_jZVU6.jpg",
          "large": "https://lain.bgm.tv/pic/crt/l/86/08/613_prsn_jZVU6.jpg",
          "medium": "https://lain.bgm.tv/r/400/pic/crt/l/86/08/613_prsn_jZVU6.jpg"
        },
        "name": "富野由悠季",
        "relation": "脚本",
        "career": [
          "producer"
        ],
        "type": 1,
        "id": 613,
        "eps": ""
      },
      {
        "images": {
          "small": "https://lain.bgm.tv/r/100/pic/crt/l/f6/a8/60901_prsn_rJfXj.jpg",
          "grid": "https://lain.bgm.tv/pic/crt/g/f6/a8/60901_prsn_rJfXj.jpg",
          "large": "https://lain.bgm.tv/pic/crt/l/f6/a8/60901_prsn_rJfXj.jpg",
          "medium": "https://lain.bgm.tv/r/400/pic/crt/l/f6/a8/60901_prsn_rJfXj.jpg"
        },
        "name": "山野浩一",
        "relation": "脚本",
        "career": [
          "writer",
          "mangaka"
        ],
        "type": 1,
        "id": 60901,
        "eps": ""
      },
      {
        "images": {
          "small": "https://lain.bgm.tv/r/100/pic/crt/l/10/93/3411_prsn_aI7Jm.jpg",
          "grid": "https://lain.bgm.tv/pic/crt/g/10/93/3411_prsn_aI7Jm.jpg",
          "large": "https://lain.bgm.tv/pic/crt/l/10/93/3411_prsn_aI7Jm.jpg",
          "medium": "https://lain.bgm.tv/r/400/pic/crt/l/10/93/3411_prsn_aI7Jm.jpg"
        },
        "name": "豊田有恒",
        "relation": "脚本",
        "career": [
          "writer",
          "producer"
        ],
        "type": 1,
        "id": 3411,
        "eps": ""
      },
      {
        "images": {
          "small": "",
          "grid": "",
          "large": "",
          "medium": ""
        },
        "name": "西牧秀夫",
        "relation": "脚本",
        "career": [
          "producer"
        ],
        "type": 1,
        "id": 3801,
        "eps": ""
      },
      {
        "images": {
          "small": "https://lain.bgm.tv/r/100/pic/crt/l/de/b8/1381_prsn_9LZP5.jpg",
          "grid": "https://lain.bgm.tv/pic/crt/g/de/b8/1381_prsn_9LZP5.jpg",
          "large": "https://lain.bgm.tv/pic/crt/l/de/b8/1381_prsn_9LZP5.jpg",
          "medium": "https://lain.bgm.tv/r/400/pic/crt/l/de/b8/1381_prsn_9LZP5.jpg"
        },
        "name": "鈴木良武",
        "relation": "脚本",
        "career": [
          "producer"
        ],
        "type": 1,
        "id": 1381,
        "eps": ""
      },
      {
        "images": {
          "small": "https://lain.bgm.tv/r/100/pic/crt/l/e9/59/967_prsn_7VbsV.jpg",
          "grid": "https://lain.bgm.tv/pic/crt/g/e9/59/967_prsn_7VbsV.jpg",
          "large": "https://lain.bgm.tv/pic/crt/l/e9/59/967_prsn_7VbsV.jpg",
          "medium": "https://lain.bgm.tv/r/400/pic/crt/l/e9/59/967_prsn_7VbsV.jpg"
        },
        "name": "坂本雄作",
        "relation": "脚本",
        "career": [
          "producer"
        ],
        "type": 1,
        "id": 967,
        "eps": ""
      },
      {
        "images": {
          "small": "https://lain.bgm.tv/r/100/pic/crt/l/83/03/1691_prsn_anidb.jpg",
          "grid": "https://lain.bgm.tv/pic/crt/g/83/03/1691_prsn_anidb.jpg",
          "large": "https://lain.bgm.tv/pic/crt/l/83/03/1691_prsn_anidb.jpg",
          "medium": "https://lain.bgm.tv/r/400/pic/crt/l/83/03/1691_prsn_anidb.jpg"
        },
        "name": "山本暎一",
        "relation": "脚本",
        "career": [
          "producer"
        ],
        "type": 1,
        "id": 1691,
        "eps": ""
      },
      {
        "images": {
          "small": "https://lain.bgm.tv/r/100/pic/crt/l/69/cd/3051_prsn_QRS2A.jpg",
          "grid": "https://lain.bgm.tv/pic/crt/g/69/cd/3051_prsn_QRS2A.jpg",
          "large": "https://lain.bgm.tv/pic/crt/l/69/cd/3051_prsn_QRS2A.jpg",
          "medium": "https://lain.bgm.tv/r/400/pic/crt/l/69/cd/3051_prsn_QRS2A.jpg"
        },
        "name": "岡崎稔",
        "relation": "脚本",
        "career": [
          "producer"
        ],
        "type": 1,
        "id": 3051,
        "eps": ""
      },
      {
        "images": {
          "small": "https://lain.bgm.tv/r/100/pic/crt/l/dc/6a/676_prsn_anidb.jpg",
          "grid": "https://lain.bgm.tv/pic/crt/g/dc/6a/676_prsn_anidb.jpg",
          "large": "https://lain.bgm.tv/pic/crt/l/dc/6a/676_prsn_anidb.jpg",
          "medium": "https://lain.bgm.tv/r/400/pic/crt/l/dc/6a/676_prsn_anidb.jpg"
        },
        "name": "鳥海尽三",
        "relation": "脚本",
        "career": [
          "producer"
        ],
        "type": 1,
        "id": 676,
        "eps": ""
      },
      {
        "images": {
          "small": "https://lain.bgm.tv/r/100/pic/crt/l/76/cf/1318_prsn_anidb.jpg",
          "grid": "https://lain.bgm.tv/pic/crt/g/76/cf/1318_prsn_anidb.jpg",
          "large": "https://lain.bgm.tv/pic/crt/l/76/cf/1318_prsn_anidb.jpg",
          "medium": "https://lain.bgm.tv/r/400/pic/crt/l/76/cf/1318_prsn_anidb.jpg"
        },
        "name": "手塚治虫",
        "relation": "总导演",
        "career": [
          "producer",
          "mangaka"
        ],
        "type": 1,
        "id": 1318,
        "eps": ""
      },
      {
        "images": {
          "small": "https://lain.bgm.tv/r/100/pic/crt/l/76/cf/1318_prsn_anidb.jpg",
          "grid": "https://lain.bgm.tv/pic/crt/g/76/cf/1318_prsn_anidb.jpg",
          "large": "https://lain.bgm.tv/pic/crt/l/76/cf/1318_prsn_anidb.jpg",
          "medium": "https://lain.bgm.tv/r/400/pic/crt/l/76/cf/1318_prsn_anidb.jpg"
        },
        "name": "手塚治虫",
        "relation": "原作",
        "career": [
          "producer",
          "mangaka"
        ],
        "type": 1,
        "id": 1318,
        "eps": ""
      }
    ],
    "characters": [
      {
        "images": {
          "small": "https://lain.bgm.tv/r/100/pic/crt/l/ea/68/14494_crt_b7H8w.jpg",
          "grid": "https://lain.bgm.tv/pic/crt/g/ea/68/14494_crt_b7H8w.jpg",
          "large": "https://lain.bgm.tv/pic/crt/l/ea/68/14494_crt_b7H8w.jpg",
          "medium": "https://lain.bgm.tv/r/400/pic/crt/l/ea/68/14494_crt_b7H8w.jpg"
        },
        "name": "アトム",
        "relation": "主角",
        "actors": [
          {
            "images": {
              "small": "https://lain.bgm.tv/r/100/pic/crt/l/c5/4a/34550_prsn_T2giQ.jpg",
              "grid": "https://lain.bgm.tv/pic/crt/g/c5/4a/34550_prsn_T2giQ.jpg",
              "large": "https://lain.bgm.tv/pic/crt/l/c5/4a/34550_prsn_T2giQ.jpg",
              "medium": "https://lain.bgm.tv/r/400/pic/crt/l/c5/4a/34550_prsn_T2giQ.jpg"
            },
            "name": "清水マリ",
            "short_summary": "",
            "career": [
              "seiyu"
            ],
            "id": 34550,
            "type": 1,
            "locked": false
          }
        ],
        "type": 1,
        "id": 14494
      },
      {
        "images": {
          "small": "https://lain.bgm.tv/r/100/pic/crt/l/d2/c1/26713_crt_5nA52.jpg",
          "grid": "https://lain.bgm.tv/pic/crt/g/d2/c1/26713_crt_5nA52.jpg",
          "large": "https://lain.bgm.tv/pic/crt/l/d2/c1/26713_crt_5nA52.jpg",
          "medium": "https://lain.bgm.tv/r/400/pic/crt/l/d2/c1/26713_crt_5nA52.jpg"
        },
        "name": "ヒゲオヤジ",
        "relation": "配角",
        "actors": [
          {
            "images": {
              "small": "https://lain.bgm.tv/r/100/pic/crt/l/62/3a/5447_seiyu_anidb.jpg",
              "grid": "https://lain.bgm.tv/pic/crt/g/62/3a/5447_seiyu_anidb.jpg",
              "large": "https://lain.bgm.tv/pic/crt/l/62/3a/5447_seiyu_anidb.jpg",
              "medium": "https://lain.bgm.tv/r/400/pic/crt/l/62/3a/5447_seiyu_anidb.jpg"
            },
            "name": "矢島正明",
            "short_summary": "日本の男性声優、ナレーター。テアトル・エコー放送映画部所属。\r\n幼少期から近所の児童に紙芝居の読み聞かせをしていた。中学時代は木戸新太郎や清水金一が出演する軽演劇に夢中になり、高校時代はムーランルージュ新宿座に通っていた。これらが声優の仕事の下地になったという。\r\n明治大学文学部演劇学科に入学。この頃「演劇の世界で生きていきたいが自分は舞台栄えがしない」と思い「声が僕の一つの劇的な表現の道具になっているのかもしれない」というような思いがあったことから放送研究会に入る。\r\n大学卒業後、1957年（昭和32年）に劇団テアトル・エコー入団。吹き替えのデビュー作は、ラジオ東京テレビ（現TBS）放送の『海賊船サルタナ』での船長役だった。\r\n1967年（昭和42年）に矢島プロダクションを設立しフリーとなる。吹き替えやアニメは草創期から数多くの作品に出演。\r\nラジオ、テレビドラマ、ドキュメンタリー、CMやテレビ番組など様々な媒体、数多くの作品でナレーターとして活躍。1975年には、三羽烏に入るナレーターとして黒沢良、城達也と共に矢島の名が挙げられている。1960年代から1980年代にかけて、日産自動車のCMナレーション（車種CM、キャッチフレーズ、日産自動車グループ各社CM）を長い期間にわたって務めていた。大正製薬の「リポビタンD」、スタジオジブリ制作映画のCMナレーションも長い期間務めており、これらは現在も継続している。\r\n2000年（平成12年）から東京シティオペラ協会の公演において、舞台に立ってナレーションを務めている。\r\n2011年、第五回声優アワード功労賞を受賞。\r\n80歳を超えてからも現役で活動している。また、声優の専門学校で後進の指導も行っている。",
            "career": [
              "seiyu"
            ],
            "id": 5447,
            "type": 1,
            "locked": false
          },
          {
            "images": {
              "small": "https://lain.bgm.tv/r/100/pic/crt/l/be/a7/58153_prsn_VFDwH.jpg",
              "grid": "https://lain.bgm.tv/pic/crt/g/be/a7/58153_prsn_VFDwH.jpg",
              "large": "https://lain.bgm.tv/pic/crt/l/be/a7/58153_prsn_VFDwH.jpg",
              "medium": "https://lain.bgm.tv/r/400/pic/crt/l/be/a7/58153_prsn_VFDwH.jpg"
            },
            "name": "和田文夫",
            "short_summary": "日本の男性俳優、声優、舞台制作者。元テアトル・エコー代表取締役社長。\r\n\r\n旧芸名は、和田 文雄（読みは同じ）。東京府出身。\r\n\r\n東京農工大学農学部卒業。\r\n\r\n1946年11月、薔薇座に入団。 『東京哀詩』の浮浪児収容所係員役が初舞台。1948年5月に薔薇座を退団。1954年9月、劇団東芸に入団し、1956年8月まで所属、同年9月にテアトル・エコー入団。1967年から1992年までテアトル・エコー社長。\r\n\r\n2010年9月6日、肺炎のため東京都板橋区の病院で死去。81歳没。",
            "career": [
              "producer",
              "seiyu",
              "actor"
            ],
            "id": 58153,
            "type": 1,
            "locked": false
          }
        ],
        "type": 1,
        "id": 26713
      },
      {
        "images": {
          "small": "https://lain.bgm.tv/r/100/pic/crt/l/81/2d/51395_crt_d8Snk.jpg",
          "grid": "https://lain.bgm.tv/pic/crt/g/81/2d/51395_crt_d8Snk.jpg",
          "large": "https://lain.bgm.tv/pic/crt/l/81/2d/51395_crt_d8Snk.jpg",
          "medium": "https://lain.bgm.tv/r/400/pic/crt/l/81/2d/51395_crt_d8Snk.jpg"
        },
        "name": "お茶の水博志",
        "relation": "配角",
        "actors": [
          {
            "images": {
              "small": "https://lain.bgm.tv/r/100/pic/crt/l/65/62/4567_seiyu_anidb.jpg",
              "grid": "https://lain.bgm.tv/pic/crt/g/65/62/4567_seiyu_anidb.jpg",
              "large": "https://lain.bgm.tv/pic/crt/l/65/62/4567_seiyu_anidb.jpg",
              "medium": "https://lain.bgm.tv/r/400/pic/crt/l/65/62/4567_seiyu_anidb.jpg"
            },
            "name": "勝田久",
            "short_summary": "2008年在第3届声优奖中获得synergy奖。\r\n2020年2月21日因衰老而去世，终年92岁。",
            "career": [
              "seiyu"
            ],
            "id": 4567,
            "type": 1,
            "locked": false
          }
        ],
        "type": 1,
        "id": 51395
      },
      {
        "images": {
          "small": "https://lain.bgm.tv/r/100/pic/crt/l/8d/f3/51396_crt_Vr5kA.jpg",
          "grid": "https://lain.bgm.tv/pic/crt/g/8d/f3/51396_crt_Vr5kA.jpg",
          "large": "https://lain.bgm.tv/pic/crt/l/8d/f3/51396_crt_Vr5kA.jpg",
          "medium": "https://lain.bgm.tv/r/400/pic/crt/l/8d/f3/51396_crt_Vr5kA.jpg"
        },
        "name": "天馬午太郎",
        "relation": "配角",
        "actors": [],
        "type": 1,
        "id": 51396
      },
      {
        "images": {
          "small": "https://lain.bgm.tv/r/100/pic/crt/l/d3/b9/132684_crt_y4BB2.jpg?r=1688255927",
          "grid": "https://lain.bgm.tv/pic/crt/g/d3/b9/132684_crt_y4BB2.jpg?r=1688255927",
          "large": "https://lain.bgm.tv/pic/crt/l/d3/b9/132684_crt_y4BB2.jpg?r=1688255927",
          "medium": "https://lain.bgm.tv/r/400/pic/crt/l/d3/b9/132684_crt_y4BB2.jpg?r=1688255927"
        },
        "name": "ウラン",
        "relation": "配角",
        "actors": [],
        "type": 1,
        "id": 132684
      },
      {
        "images": {
          "small": "https://lain.bgm.tv/r/100/pic/crt/l/7a/2c/140916_crt_JvPxM.jpg",
          "grid": "https://lain.bgm.tv/pic/crt/g/7a/2c/140916_crt_JvPxM.jpg",
          "large": "https://lain.bgm.tv/pic/crt/l/7a/2c/140916_crt_JvPxM.jpg",
          "medium": "https://lain.bgm.tv/r/400/pic/crt/l/7a/2c/140916_crt_JvPxM.jpg"
        },
        "name": "田鷲",
        "relation": "配角",
        "actors": [
          {
            "images": {
              "small": "https://lain.bgm.tv/r/100/pic/crt/l/c8/c4/946_prsn_anidb.jpg",
              "grid": "https://lain.bgm.tv/pic/crt/g/c8/c4/946_prsn_anidb.jpg",
              "large": "https://lain.bgm.tv/pic/crt/l/c8/c4/946_prsn_anidb.jpg",
              "medium": "https://lain.bgm.tv/r/400/pic/crt/l/c8/c4/946_prsn_anidb.jpg"
            },
            "name": "千葉耕市",
            "short_summary": "日本の男性声優、俳優、音響監督。岩手県出身[1]。日本大学卒業。最終所属は同人舎プロダクション。特技は東北弁。\r\n\r\n本名は千葉 治（ちば おさむ）。また一部の作品においては千葉 耕一とクレジットされることもあった。\r\n\r\nラジオドラマ創成期からの名優で、独立してから晩年に至るまで長く音響監督を務めてきた。音響監督としての代表作はサンライズの勇者シリーズ等。役者出身だけに的確なアドバイスなど若手の声優たちとの親交においてもとても信頼ある人物であった。\r\n\r\n没後に出た『ガオガイガーFINAL サウンドトラック2』のパッケージ中には密かに、英語で「この作品を千葉耕市氏に捧げる」と記されている。作品に対して命の火が消えようとも力を尽くした、恩師・先輩への製作者、役者らの敬意と感謝、追悼の念が込められている。\r\n\r\nその他に、アニメ『イソップワールド』（1999年にテレビ東京系で放映）を担当中に体調を崩し、入退院を繰り替えしたが、同番組の打ち上げパーティーでは「僕は（病気で）声を失った時に、“俳優としての千葉耕市は死んだ（終わった）”と思った。でも“演出家としての千葉耕市はまだ生きている”と考えるようになった。だからこそ今日まで自分を奮い立たせることができたんだ。人間、希望を捨ててはいけないのだよ」（注：“声を失った”とは、舞台等で観客の耳に届くほどの声量が出せなくなったという意味）と語った。\r\n\r\n妻は音響制作プロデューサー、『クルーズ』社長の千田啓子。",
            "career": [
              "producer",
              "seiyu"
            ],
            "id": 946,
            "type": 1,
            "locked": false
          }
        ],
        "type": 1,
        "id": 140916
      },
      {
        "images": {
          "small": "https://lain.bgm.tv/r/100/pic/crt/l/54/34/140917_crt_ifzzx.jpg",
          "grid": "https://lain.bgm.tv/pic/crt/g/54/34/140917_crt_ifzzx.jpg",
          "large": "https://lain.bgm.tv/pic/crt/l/54/34/140917_crt_ifzzx.jpg",
          "medium": "https://lain.bgm.tv/r/400/pic/crt/l/54/34/140917_crt_ifzzx.jpg"
        },
        "name": "中村",
        "relation": "配角",
        "actors": [],
        "type": 1,
        "id": 140917
      }
    ],
    "subjects": [
      {
        "images": {
          "small": "",
          "grid": "",
          "large": "",
          "medium": "",
          "common": ""
        },
        "name": "鉄腕アトム 新作TVアニメ",
        "name_cn": "铁臂阿童木 新作",
        "relation": "不同演绎",
        "type": 2,
        "id": 226541
      },
      {
        "images": {
          "small": "https://lain.bgm.tv/r/200/pic/cover/l/96/0b/573385_BA02z.jpg",
          "grid": "https://lain.bgm.tv/r/100/pic/cover/l/96/0b/573385_BA02z.jpg",
          "large": "https://lain.bgm.tv/pic/cover/l/96/0b/573385_BA02z.jpg",
          "medium": "https://lain.bgm.tv/r/800/pic/cover/l/96/0b/573385_BA02z.jpg",
          "common": "https://lain.bgm.tv/r/400/pic/cover/l/96/0b/573385_BA02z.jpg"
        },
        "name": "やわらかアトム",
        "name_cn": "柔软阿童木",
        "relation": "联动",
        "type": 2,
        "id": 573385
      },
      {
        "images": {
          "small": "https://lain.bgm.tv/r/200/pic/cover/l/45/73/560627_OnT8F.jpg",
          "grid": "https://lain.bgm.tv/r/100/pic/cover/l/45/73/560627_OnT8F.jpg",
          "large": "https://lain.bgm.tv/pic/cover/l/45/73/560627_OnT8F.jpg",
          "medium": "https://lain.bgm.tv/r/800/pic/cover/l/45/73/560627_OnT8F.jpg",
          "common": "https://lain.bgm.tv/r/400/pic/cover/l/45/73/560627_OnT8F.jpg"
        },
        "name": "鉄腕アトム（光文社カッパコミックス版）",
        "name_cn": "",
        "relation": "书籍",
        "type": 1,
        "id": 560627
      },
      {
        "images": {
          "small": "https://lain.bgm.tv/r/200/pic/cover/l/60/6c/456305_J945P.jpg",
          "grid": "https://lain.bgm.tv/r/100/pic/cover/l/60/6c/456305_J945P.jpg",
          "large": "https://lain.bgm.tv/pic/cover/l/60/6c/456305_J945P.jpg",
          "medium": "https://lain.bgm.tv/r/800/pic/cover/l/60/6c/456305_J945P.jpg",
          "common": "https://lain.bgm.tv/r/400/pic/cover/l/60/6c/456305_J945P.jpg"
        },
        "name": "元梦之星",
        "name_cn": "元梦之星",
        "relation": "游戏",
        "type": 4,
        "id": 456305
      },
      {
        "images": {
          "small": "https://lain.bgm.tv/r/200/pic/cover/l/e8/20/425949_jlUwN.jpg",
          "grid": "https://lain.bgm.tv/r/100/pic/cover/l/e8/20/425949_jlUwN.jpg",
          "large": "https://lain.bgm.tv/pic/cover/l/e8/20/425949_jlUwN.jpg",
          "medium": "https://lain.bgm.tv/r/800/pic/cover/l/e8/20/425949_jlUwN.jpg",
          "common": "https://lain.bgm.tv/r/400/pic/cover/l/e8/20/425949_jlUwN.jpg"
        },
        "name": "鉄腕アトム 地球防衛隊",
        "name_cn": "铁臂阿童木 地球防卫队",
        "relation": "总集篇",
        "type": 2,
        "id": 425949
      },
      {
        "images": {
          "small": "https://lain.bgm.tv/r/200/pic/cover/l/88/1c/425942_JVFGc.jpg",
          "grid": "https://lain.bgm.tv/r/100/pic/cover/l/88/1c/425942_JVFGc.jpg",
          "large": "https://lain.bgm.tv/pic/cover/l/88/1c/425942_JVFGc.jpg",
          "medium": "https://lain.bgm.tv/r/800/pic/cover/l/88/1c/425942_JVFGc.jpg",
          "common": "https://lain.bgm.tv/r/400/pic/cover/l/88/1c/425942_JVFGc.jpg"
        },
        "name": "鉄腕アトム〜地球最後の日〜",
        "name_cn": "铁臂阿童木 地球最后一日",
        "relation": "不同演绎",
        "type": 2,
        "id": 425942
      },
      {
        "images": {
          "small": "https://lain.bgm.tv/r/200/pic/cover/l/48/12/421833_W3388.jpg",
          "grid": "https://lain.bgm.tv/r/100/pic/cover/l/48/12/421833_W3388.jpg",
          "large": "https://lain.bgm.tv/pic/cover/l/48/12/421833_W3388.jpg",
          "medium": "https://lain.bgm.tv/r/800/pic/cover/l/48/12/421833_W3388.jpg",
          "common": "https://lain.bgm.tv/r/400/pic/cover/l/48/12/421833_W3388.jpg"
        },
        "name": "鉄腕アトム / 新撰組",
        "name_cn": "铁臂阿童木 / 新选组",
        "relation": "不同演绎",
        "type": 2,
        "id": 421833
      },
      {
        "images": {
          "small": "https://lain.bgm.tv/r/200/pic/cover/l/86/18/388524_a7DUO.jpg",
          "grid": "https://lain.bgm.tv/r/100/pic/cover/l/86/18/388524_a7DUO.jpg",
          "large": "https://lain.bgm.tv/pic/cover/l/86/18/388524_a7DUO.jpg",
          "medium": "https://lain.bgm.tv/r/800/pic/cover/l/86/18/388524_a7DUO.jpg",
          "common": "https://lain.bgm.tv/r/400/pic/cover/l/86/18/388524_a7DUO.jpg"
        },
        "name": "Astroboy Reboot",
        "name_cn": "铁臂阿童木",
        "relation": "不同演绎",
        "type": 2,
        "id": 388524
      },
      {
        "images": {
          "small": "https://lain.bgm.tv/r/200/pic/cover/l/b7/22/360126_LLwjU.jpg",
          "grid": "https://lain.bgm.tv/r/100/pic/cover/l/b7/22/360126_LLwjU.jpg",
          "large": "https://lain.bgm.tv/pic/cover/l/b7/22/360126_LLwjU.jpg",
          "medium": "https://lain.bgm.tv/r/800/pic/cover/l/b7/22/360126_LLwjU.jpg",
          "common": "https://lain.bgm.tv/r/400/pic/cover/l/b7/22/360126_LLwjU.jpg"
        },
        "name": "鉄腕アトム 宇宙の勇者",
        "name_cn": "铁臂阿童木 宇宙的勇者",
        "relation": "总集篇",
        "type": 2,
        "id": 360126
      },
      {
        "images": {
          "small": "https://lain.bgm.tv/r/200/pic/cover/l/98/c3/3151_F90q0.jpg",
          "grid": "https://lain.bgm.tv/r/100/pic/cover/l/98/c3/3151_F90q0.jpg",
          "large": "https://lain.bgm.tv/pic/cover/l/98/c3/3151_F90q0.jpg",
          "medium": "https://lain.bgm.tv/r/800/pic/cover/l/98/c3/3151_F90q0.jpg",
          "common": "https://lain.bgm.tv/r/400/pic/cover/l/98/c3/3151_F90q0.jpg"
        },
        "name": "Astro Boy",
        "name_cn": "阿童木",
        "relation": "不同演绎",
        "type": 2,
        "id": 3151
      },
      {
        "images": {
          "small": "https://lain.bgm.tv/r/200/pic/cover/l/ef/aa/217198_XPYel.jpg",
          "grid": "https://lain.bgm.tv/r/100/pic/cover/l/ef/aa/217198_XPYel.jpg",
          "large": "https://lain.bgm.tv/pic/cover/l/ef/aa/217198_XPYel.jpg",
          "medium": "https://lain.bgm.tv/r/800/pic/cover/l/ef/aa/217198_XPYel.jpg",
          "common": "https://lain.bgm.tv/r/400/pic/cover/l/ef/aa/217198_XPYel.jpg"
        },
        "name": "絵師神の絆",
        "name_cn": "",
        "relation": "游戏",
        "type": 4,
        "id": 217198
      },
      {
        "images": {
          "small": "https://lain.bgm.tv/r/200/pic/cover/l/d3/6a/217021_oRobJ.jpg",
          "grid": "https://lain.bgm.tv/r/100/pic/cover/l/d3/6a/217021_oRobJ.jpg",
          "large": "https://lain.bgm.tv/pic/cover/l/d3/6a/217021_oRobJ.jpg",
          "medium": "https://lain.bgm.tv/r/800/pic/cover/l/d3/6a/217021_oRobJ.jpg",
          "common": "https://lain.bgm.tv/r/400/pic/cover/l/d3/6a/217021_oRobJ.jpg"
        },
        "name": "PLUTO",
        "name_cn": "冥王",
        "relation": "不同演绎",
        "type": 2,
        "id": 217021
      },
      {
        "images": {
          "small": "https://lain.bgm.tv/r/200/pic/cover/l/33/0d/184059_T2CtF.jpg",
          "grid": "https://lain.bgm.tv/r/100/pic/cover/l/33/0d/184059_T2CtF.jpg",
          "large": "https://lain.bgm.tv/pic/cover/l/33/0d/184059_T2CtF.jpg",
          "medium": "https://lain.bgm.tv/r/800/pic/cover/l/33/0d/184059_T2CtF.jpg",
          "common": "https://lain.bgm.tv/r/400/pic/cover/l/33/0d/184059_T2CtF.jpg"
        },
        "name": "アトム ザ・ビギニング",
        "name_cn": "阿童木起源",
        "relation": "前传",
        "type": 2,
        "id": 184059
      },
      {
        "images": {
          "small": "https://lain.bgm.tv/r/200/pic/cover/l/46/cb/145687_LLF5y.jpg",
          "grid": "https://lain.bgm.tv/r/100/pic/cover/l/46/cb/145687_LLF5y.jpg",
          "large": "https://lain.bgm.tv/pic/cover/l/46/cb/145687_LLF5y.jpg",
          "medium": "https://lain.bgm.tv/r/800/pic/cover/l/46/cb/145687_LLF5y.jpg",
          "common": "https://lain.bgm.tv/r/400/pic/cover/l/46/cb/145687_LLF5y.jpg"
        },
        "name": "鉄腕アトム / ロボットマーチ",
        "name_cn": "",
        "relation": "片头曲",
        "type": 3,
        "id": 145687
      },
      {
        "images": {
          "small": "",
          "grid": "",
          "large": "",
          "medium": "",
          "common": ""
        },
        "name": "鉄腕アトム",
        "name_cn": "铁臂阿童木",
        "relation": "三次元",
        "type": 6,
        "id": 124626
      },
      {
        "images": {
          "small": "https://lain.bgm.tv/r/200/pic/cover/l/bf/05/73768_jp.jpg",
          "grid": "https://lain.bgm.tv/r/100/pic/cover/l/bf/05/73768_jp.jpg",
          "large": "https://lain.bgm.tv/pic/cover/l/bf/05/73768_jp.jpg",
          "medium": "https://lain.bgm.tv/r/800/pic/cover/l/bf/05/73768_jp.jpg",
          "common": "https://lain.bgm.tv/r/400/pic/cover/l/bf/05/73768_jp.jpg"
        },
        "name": "「鉄腕アトム」オリジナルサウンドトラック",
        "name_cn": "",
        "relation": "原声集",
        "type": 3,
        "id": 73768
      },
      {
        "images": {
          "small": "https://lain.bgm.tv/r/200/pic/cover/l/d1/ad/28288_K0TsB.jpg",
          "grid": "https://lain.bgm.tv/r/100/pic/cover/l/d1/ad/28288_K0TsB.jpg",
          "large": "https://lain.bgm.tv/pic/cover/l/d1/ad/28288_K0TsB.jpg",
          "medium": "https://lain.bgm.tv/r/800/pic/cover/l/d1/ad/28288_K0TsB.jpg",
          "common": "https://lain.bgm.tv/r/400/pic/cover/l/d1/ad/28288_K0TsB.jpg"
        },
        "name": "ASTRO BOY 鉄腕アトム",
        "name_cn": "铁臂阿童木",
        "relation": "不同演绎",
        "type": 2,
        "id": 28288
      },
      {
        "images": {
          "small": "https://lain.bgm.tv/r/200/pic/cover/l/4e/a4/28287_diMmW.jpg",
          "grid": "https://lain.bgm.tv/r/100/pic/cover/l/4e/a4/28287_diMmW.jpg",
          "large": "https://lain.bgm.tv/pic/cover/l/4e/a4/28287_diMmW.jpg",
          "medium": "https://lain.bgm.tv/r/800/pic/cover/l/4e/a4/28287_diMmW.jpg",
          "common": "https://lain.bgm.tv/r/400/pic/cover/l/4e/a4/28287_diMmW.jpg"
        },
        "name": "鉄腕アトム",
        "name_cn": "铁臂阿童木",
        "relation": "不同演绎",
        "type": 2,
        "id": 28287
      }
    ],
    "updatedAt": "2025-10-21T11:28:56.496Z"
  }
]