[
  {
    "id": 34281,
    "title": "战斗机甲萨芬格尔",
    "platform": "TV",
    "onair_date": "1982-02-06",
    "rating": {
      "score": 7.5,
      "rank": 1134
    },
    "poster": "https://lain.bgm.tv/pic/cover/l/85/ed/34281_kFyNN.jpg",
    "images": [
      {
        "provider": "bgm",
        "quality": "large",
        "src": "https://lain.bgm.tv/pic/cover/l/85/ed/34281_kFyNN.jpg"
      },
      {
        "provider": "bgm",
        "quality": "common",
        "src": "https://lain.bgm.tv/r/400/pic/cover/l/85/ed/34281_kFyNN.jpg"
      },
      {
        "provider": "bgm",
        "quality": "medium",
        "src": "https://lain.bgm.tv/r/800/pic/cover/l/85/ed/34281_kFyNN.jpg"
      },
      {
        "provider": "bgm",
        "quality": "small",
        "src": "https://lain.bgm.tv/r/200/pic/cover/l/85/ed/34281_kFyNN.jpg"
      },
      {
        "provider": "bgm",
        "quality": "grid",
        "src": "https://lain.bgm.tv/r/100/pic/cover/l/85/ed/34281_kFyNN.jpg"
      }
    ],
    "summary": "惑星ゾラと呼ばれる地球。ここは盗んだ物も3日間守り通して逃げのびれば自分の物になる、という掟が通る無法の星。\n　　その大地を駆ける暴走族、サンドラット団は、ウォーカーマシンに襲われたところを、負傷した少年ジロンに助けられた。サンドラットの女リーダーのラグは、このジロンに興味津々。なにしろ手負いの身ながらたった一人で、ブルーストーンの運び屋キャリング・カーゴが開くバザーに乗り込み、ウォーカーマシンを分捕ろうというのだ。バザーにはキャリングの用心棒や、無法の星に似つかわしい荒くれ者ばかりが揃っている。そんな所に乗り込んで行こうと言うジロンが目指す獲物は、なんと！　キャリングの新鋭ウォーカーマシン「ザブングル」！！",
    "alias": [
      "Blue Gale XABUNGLE",
      "Combat Mecha Xabungle",
      "Sentou Mecha Xabungle",
      "Xabungle",
      "战斗机甲萨芬格尔",
      "戦闘 メカザブングル",
      "戦闘メカザブングル",
      "柴油机"
    ],
    "tags": [
      "1982年2月",
      "80年代",
      "SUNRISE",
      "TV",
      "五武冬史",
      "原创",
      "富野由悠季",
      "搞笑",
      "机战",
      "湖川友谦",
      "科幻",
      "萝卜"
    ],
    "search": {
      "include": [
        "Blue Gale XABUNGLE",
        "Combat Mecha Xabungle",
        "Sentou Mecha Xabungle",
        "Xabungle",
        "战斗机甲萨芬格尔",
        "戦闘 メカザブングル",
        "戦闘メカザブングル",
        "柴油机"
      ]
    }
  },
  {
    "id": 37299,
    "title": "逆转一发人",
    "platform": "TV",
    "onair_date": "1982-02-13",
    "rating": {
      "score": 6.5,
      "rank": 0
    },
    "poster": "https://lain.bgm.tv/pic/cover/l/a2/a5/37299_1y1PC.jpg",
    "images": [
      {
        "provider": "bgm",
        "quality": "large",
        "src": "https://lain.bgm.tv/pic/cover/l/a2/a5/37299_1y1PC.jpg"
      },
      {
        "provider": "bgm",
        "quality": "common",
        "src": "https://lain.bgm.tv/r/400/pic/cover/l/a2/a5/37299_1y1PC.jpg"
      },
      {
        "provider": "bgm",
        "quality": "medium",
        "src": "https://lain.bgm.tv/r/800/pic/cover/l/a2/a5/37299_1y1PC.jpg"
      },
      {
        "provider": "bgm",
        "quality": "small",
        "src": "https://lain.bgm.tv/r/200/pic/cover/l/a2/a5/37299_1y1PC.jpg"
      },
      {
        "provider": "bgm",
        "quality": "grid",
        "src": "https://lain.bgm.tv/r/100/pic/cover/l/a2/a5/37299_1y1PC.jpg"
      }
    ],
    "summary": "时间飞船第6作\n舞台は1990年。劇中では西暦と呼ばれていないため、どの時代なのかは不明。\nタイムリース社は、依頼があれば時空を越えて、過去でも未来でも現代でも世界各地に荷物を届ける、業界のトップ企業。一方業界第2位の大手・シャレコーベリース社だが、タイムリース社本社のすぐそばにあるオストアンデル北部支社は業績絶不調。会長のコン・コルドーは、ムンムンを始めとした社員にタイムリース社の営業妨害を命じた。ムンムンたちは「クリーン悪トリオ」となり、営業妨害を続ける。ハル坊がピンチ通信を出すと必ずイッパツマンが助けにやって来る。",
    "alias": [
      "タイムボカンシリーズ 逆転イッパツマン",
      "一發合身逆轉王",
      "逆转一发人",
      "逆转一发超人"
    ],
    "tags": [],
    "search": {
      "include": [
        "タイムボカンシリーズ 逆転イッパツマン",
        "一發合身逆轉王",
        "逆转一发人",
        "逆转一发超人"
      ]
    }
  }
]