[
  {
    "id": 158777,
    "title": "小露美",
    "data": {
      "id": 158777,
      "title": "小露美",
      "platform": "剧场版",
      "onair_date": "1970-03-17",
      "alias": [
        "Little Remi and Famous Dog Capi",
        "ちびっ子レミと名犬カピ",
        "小露美"
      ],
      "rating": {
        "score": 6.1,
        "rank": 0
      },
      "summary": "エクトール・アンリ・マロの名作『家なき子』をアニメ化した作品。仮題は『家なき子 母をたずねて』。\r\n原作は悲劇的ととらわれているが、本作は主人公レミが逆境から立ち上がっていく姿を、バイタリティに脚色している。また劇中では、泰西名画の西洋画調の美術を背景にし、更に実写を合成して効果を上げた。\r\nなお本作はその後、『ちびっ子レミと名犬カピより 家なき子』と改題し、上映時間を短縮して、1975年7月26日封切りの『東映まんがまつり』内で上映。",
      "poster": "https://lain.bgm.tv/pic/cover/l/93/99/158777_24CmM.jpg",
      "images": [
        {
          "provider": "bgm",
          "quality": "large",
          "src": "https://lain.bgm.tv/pic/cover/l/93/99/158777_24CmM.jpg"
        },
        {
          "provider": "bgm",
          "quality": "common",
          "src": "https://lain.bgm.tv/r/400/pic/cover/l/93/99/158777_24CmM.jpg"
        },
        {
          "provider": "bgm",
          "quality": "medium",
          "src": "https://lain.bgm.tv/r/800/pic/cover/l/93/99/158777_24CmM.jpg"
        },
        {
          "provider": "bgm",
          "quality": "small",
          "src": "https://lain.bgm.tv/r/200/pic/cover/l/93/99/158777_24CmM.jpg"
        },
        {
          "provider": "bgm",
          "quality": "grid",
          "src": "https://lain.bgm.tv/r/100/pic/cover/l/93/99/158777_24CmM.jpg"
        }
      ],
      "tags": []
    },
    "search": {
      "include": [
        "Little Remi and Famous Dog Capi",
        "ちびっ子レミと名犬カピ",
        "小露美"
      ]
    },
    "updatedAt": "2025-10-18T10:30:56.507Z"
  },
  {
    "id": 274337,
    "title": "巨人の星 大リーグボール",
    "data": {
      "id": 274337,
      "title": "巨人の星 大リーグボール",
      "platform": "剧场版",
      "onair_date": "1970-03-21",
      "alias": [
        "巨人の星 大リーグボール"
      ],
      "rating": {
        "score": 6.8,
        "rank": 0
      },
      "summary": "「東宝チャンピオンまつり」で上映。飛雄馬がデビュー戦で左門に打たれ、大リーグボール1号（改良前）を誕生するまでを描いた第70話から第77話を再編集ブローアップ。\r\n同時上映は『キングコング対ゴジラ』（リバイバル）・『アタックNo.1』・『やさしいライオン』の3本。",
      "poster": "https://lain.bgm.tv/pic/cover/l/3e/e7/274337_Xd635.jpg",
      "images": [
        {
          "provider": "bgm",
          "quality": "large",
          "src": "https://lain.bgm.tv/pic/cover/l/3e/e7/274337_Xd635.jpg"
        },
        {
          "provider": "bgm",
          "quality": "common",
          "src": "https://lain.bgm.tv/r/400/pic/cover/l/3e/e7/274337_Xd635.jpg"
        },
        {
          "provider": "bgm",
          "quality": "medium",
          "src": "https://lain.bgm.tv/r/800/pic/cover/l/3e/e7/274337_Xd635.jpg"
        },
        {
          "provider": "bgm",
          "quality": "small",
          "src": "https://lain.bgm.tv/r/200/pic/cover/l/3e/e7/274337_Xd635.jpg"
        },
        {
          "provider": "bgm",
          "quality": "grid",
          "src": "https://lain.bgm.tv/r/100/pic/cover/l/3e/e7/274337_Xd635.jpg"
        }
      ],
      "tags": []
    },
    "search": {
      "include": [
        "巨人の星 大リーグボール"
      ]
    },
    "updatedAt": "2025-10-18T10:42:22.848Z"
  },
  {
    "id": 378799,
    "title": "排球甜心 剧场版",
    "data": {
      "id": 378799,
      "title": "排球甜心 剧场版",
      "platform": "剧场版",
      "onair_date": "1970-03-21",
      "alias": [
        "劇場版 アタックNo.1",
        "排球甜心 剧场版"
      ],
      "rating": {
        "score": 0,
        "rank": 0
      },
      "summary": "　浦野千賀子の原作を、「巨人の星(1969)」の辻真先ほか三名が共同脚色し、岡部英二と黒川文夫が演出を担当したまんが映画。作画監督は竹内留吉が担当。\r\n　鮎原こずえは富士見学園に転校早々、劣等生グループの番長にされた。バレー部への入部を断ったこずえは劣等生グループで即席バレー部をつくりチームワーク抜群の試合運びでレギュラーチームを破った。そしてバレー部に入ったこずえはキャプテンに推薦された。だがある日、天才的技術をもったみどりが転校してきて、バレー部に入り、財閥の父の力でキャプテンの座を奪ってしまう。しかしみどりの身勝手なプレーで試合に負けてしまい、スパルタ訓練の本郷先生をコーチに迎えた。名門松島中学との試合中、みどりはチームワークの重要さを知り、こずえとのアタック・コンビを完成させた。この二人の活躍で、松島中学を破った富士見学園バレー部は再びキャプテンに選ばれたこずえを中心に日本一めざして歩み出した。",
      "poster": "https://lain.bgm.tv/pic/cover/l/80/c6/378799_Ov5qg.jpg",
      "images": [
        {
          "provider": "bgm",
          "quality": "large",
          "src": "https://lain.bgm.tv/pic/cover/l/80/c6/378799_Ov5qg.jpg"
        },
        {
          "provider": "bgm",
          "quality": "common",
          "src": "https://lain.bgm.tv/r/400/pic/cover/l/80/c6/378799_Ov5qg.jpg"
        },
        {
          "provider": "bgm",
          "quality": "medium",
          "src": "https://lain.bgm.tv/r/800/pic/cover/l/80/c6/378799_Ov5qg.jpg"
        },
        {
          "provider": "bgm",
          "quality": "small",
          "src": "https://lain.bgm.tv/r/200/pic/cover/l/80/c6/378799_Ov5qg.jpg"
        },
        {
          "provider": "bgm",
          "quality": "grid",
          "src": "https://lain.bgm.tv/r/100/pic/cover/l/80/c6/378799_Ov5qg.jpg"
        }
      ],
      "tags": []
    },
    "search": {
      "include": [
        "劇場版 アタックNo.1",
        "排球甜心 剧场版"
      ]
    },
    "updatedAt": "2025-10-18T10:51:27.153Z"
  }
]