[
  {
    "id": 338655,
    "title": "冰雪极境",
    "platform": "WEB",
    "onair_date": "2023-02-02",
    "rating": {
      "score": 4.6,
      "rank": 8551
    },
    "poster": "https://lain.bgm.tv/pic/cover/l/e4/65/338655_2VnUz.jpg",
    "images": [
      {
        "provider": "bgm",
        "quality": "large",
        "src": "https://lain.bgm.tv/pic/cover/l/e4/65/338655_2VnUz.jpg"
      },
      {
        "provider": "bgm",
        "quality": "common",
        "src": "https://lain.bgm.tv/r/400/pic/cover/l/e4/65/338655_2VnUz.jpg"
      },
      {
        "provider": "bgm",
        "quality": "medium",
        "src": "https://lain.bgm.tv/r/800/pic/cover/l/e4/65/338655_2VnUz.jpg"
      },
      {
        "provider": "bgm",
        "quality": "small",
        "src": "https://lain.bgm.tv/r/200/pic/cover/l/e4/65/338655_2VnUz.jpg"
      },
      {
        "provider": "bgm",
        "quality": "grid",
        "src": "https://lain.bgm.tv/r/100/pic/cover/l/e4/65/338655_2VnUz.jpg"
      }
    ],
    "summary": "白鳥座の角にある氷と雪に覆われた不毛な惑星。地下の暗闇から突如として謎の生物が現れ、住民たちを襲い始める。\n明日が見えない恐怖の中で、人間たちは生き延びることができるのか？",
    "alias": [
      "MAKE MY DAY",
      "メイク マイ デイ",
      "冰雪极境"
    ],
    "tags": [
      "2023年1月",
      "Five",
      "Netflix",
      "TV",
      "WEB",
      "原创",
      "本多真",
      "科幻"
    ],
    "search": {
      "include": [
        "MAKE MY DAY",
        "メイク マイ デイ",
        "冰雪极境"
      ]
    }
  },
  {
    "id": 353792,
    "title": "蓝色巨星",
    "platform": "剧场版",
    "onair_date": "2023-02-17",
    "rating": {
      "score": 7.4,
      "rank": 1054
    },
    "poster": "https://lain.bgm.tv/pic/cover/l/32/53/353792_VE3lM.jpg",
    "images": [
      {
        "provider": "bgm",
        "quality": "large",
        "src": "https://lain.bgm.tv/pic/cover/l/32/53/353792_VE3lM.jpg"
      },
      {
        "provider": "bgm",
        "quality": "common",
        "src": "https://lain.bgm.tv/r/400/pic/cover/l/32/53/353792_VE3lM.jpg"
      },
      {
        "provider": "bgm",
        "quality": "medium",
        "src": "https://lain.bgm.tv/r/800/pic/cover/l/32/53/353792_VE3lM.jpg"
      },
      {
        "provider": "bgm",
        "quality": "small",
        "src": "https://lain.bgm.tv/r/200/pic/cover/l/32/53/353792_VE3lM.jpg"
      },
      {
        "provider": "bgm",
        "quality": "grid",
        "src": "https://lain.bgm.tv/r/100/pic/cover/l/32/53/353792_VE3lM.jpg"
      }
    ],
    "summary": "「オレは世界一のジャズプレーヤーになる。」\n\n ジャズに魅了され、テナーサックスを始めた仙台の高校生・宮本大（ミヤモトダイ）。\n雨の日も風の日も、毎日たったひとりで何年も、河原でテナーサックスを吹き続けてきた。\n\n卒業を機にジャズのため、上京。高校の同級生・玉田俊二（タマダシュンジ）のアパートに転がり込んだ大は、ある日訪れたライブハウスで同世代の凄腕ピアニスト・沢辺雪祈（サワベユキノリ）と出会う。\n\n「組もう。」\n\n大は雪祈をバンドに誘う。はじめは本気で取り合わない雪祈だったが、聴く者を圧倒する大のサックスに胸を打たれ、二人はバンドを組むことに。そこへ大の熱さに感化されドラムを始めた玉田が加わり、三人は“JASS”を結成する。\n\n楽譜も読めず、ジャズの知識もなかったが、ひたすらに、全力で吹いてきた大。幼い頃からジャズに全てを捧げてきた雪祈。初心者の玉田。\n\nトリオの目標は、日本最高のジャズクラブ「So Blue」に出演し、日本のジャズシーンを変えること。 無謀と思われる目標に、必死に挑みながら成長していく “JASS”は、次第に注目を集めるようになる。「So Blue」でのライブ出演にも可能性が見え始め、目まぐるしい躍進がこのまま続いていくかに思えたが、ある思いもよらない出来事が起こり……\n\n情熱の限りを音楽に注いだ青春。その果てに見える景色とはー。",
    "alias": [
      "BLUE GIANT",
      "ブルージャイアント",
      "蓝色巨星"
    ],
    "tags": [
      "2023年2月",
      "NUT",
      "jazz",
      "上原ひろみ",
      "剧场版",
      "动画电影",
      "励志",
      "漫改",
      "热血",
      "爵士",
      "立川譲",
      "立川让",
      "音乐"
    ],
    "search": {
      "include": [
        "BLUE GIANT",
        "ブルージャイアント",
        "蓝色巨星"
      ]
    }
  },
  {
    "id": 376008,
    "title": "电影 佐佐木与宫野ー毕业篇ー",
    "platform": "剧场版",
    "onair_date": "2023-02-17",
    "rating": {
      "score": 6.5,
      "rank": 4119
    },
    "poster": "https://lain.bgm.tv/pic/cover/l/fb/59/376008_JUtHw.jpg",
    "images": [
      {
        "provider": "bgm",
        "quality": "large",
        "src": "https://lain.bgm.tv/pic/cover/l/fb/59/376008_JUtHw.jpg"
      },
      {
        "provider": "bgm",
        "quality": "common",
        "src": "https://lain.bgm.tv/r/400/pic/cover/l/fb/59/376008_JUtHw.jpg"
      },
      {
        "provider": "bgm",
        "quality": "medium",
        "src": "https://lain.bgm.tv/r/800/pic/cover/l/fb/59/376008_JUtHw.jpg"
      },
      {
        "provider": "bgm",
        "quality": "small",
        "src": "https://lain.bgm.tv/r/200/pic/cover/l/fb/59/376008_JUtHw.jpg"
      },
      {
        "provider": "bgm",
        "quality": "grid",
        "src": "https://lain.bgm.tv/r/100/pic/cover/l/fb/59/376008_JUtHw.jpg"
      }
    ],
    "summary": "「だれかを好きになること」を応援してくれる\n爽やか青春男子高校生LIFE。\n女顔がコンプレックスな腐男子の宮野由美（みやのよしかず）は、\nある夏の日、ちょっとだけ不良な先輩・佐々木秀鳴（ささきしゅうめい）と出会った。\nBL漫画の貸し借りから始まった、佐々木と宮野のちょっとした日常。\n移り行く季節の中、二人の距離は変化して……。\nそしてたどりついた、お互いの「好き」の気持ち。\n\n季節は冬になり、佐々木は受験をむかえることに。\n受験が終われば、卒業式はもう目の前。\n「佐々木先輩が、卒業する―――」\n勉強に集中する佐々木を気遣い、登下校で二人の時間を大切にする宮野だけれど……\n\n変わっていくこと。変わらないこと。\nあたたかくて愛おしい、二人の高校生活は―――",
    "alias": [
      "Eiga Sasaki to Miyano: Sotsugyou Hen",
      "Sasaki and Miyano: Graduation",
      "映画 佐々木と宮野 -卒業編-",
      "映画 佐々木と宮野ー卒業編ー",
      "电影 佐佐木与宫野ー毕业篇ー"
    ],
    "tags": [
      "2023年1月",
      "BL",
      "studiodeen",
      "剧场版",
      "恋爱",
      "校园",
      "漫改",
      "耽美"
    ],
    "search": {
      "include": [
        "Eiga Sasaki to Miyano: Sotsugyou Hen",
        "Sasaki and Miyano: Graduation",
        "映画 佐々木と宮野 -卒業編-",
        "映画 佐々木と宮野ー卒業編ー",
        "电影 佐佐木与宫野ー毕业篇ー"
      ]
    }
  },
  {
    "id": 390395,
    "title": "红白黑黄 第九季",
    "platform": "WEB",
    "onair_date": "2023-02-18",
    "rating": {
      "score": 5.4,
      "rank": 8185
    },
    "poster": "https://lain.bgm.tv/pic/cover/l/87/d2/390395_xO8oX.jpg",
    "images": [
      {
        "provider": "bgm",
        "quality": "large",
        "src": "https://lain.bgm.tv/pic/cover/l/87/d2/390395_xO8oX.jpg"
      },
      {
        "provider": "bgm",
        "quality": "common",
        "src": "https://lain.bgm.tv/r/400/pic/cover/l/87/d2/390395_xO8oX.jpg"
      },
      {
        "provider": "bgm",
        "quality": "medium",
        "src": "https://lain.bgm.tv/r/800/pic/cover/l/87/d2/390395_xO8oX.jpg"
      },
      {
        "provider": "bgm",
        "quality": "small",
        "src": "https://lain.bgm.tv/r/200/pic/cover/l/87/d2/390395_xO8oX.jpg"
      },
      {
        "provider": "bgm",
        "quality": "grid",
        "src": "https://lain.bgm.tv/r/100/pic/cover/l/87/d2/390395_xO8oX.jpg"
      }
    ],
    "summary": "The future-fantasy world of Remnant is filled with ravenous monsters, treacherous terrain, and more villains than you can shake a sniper-scythe at. Fortunately, Beacon Academy is training Huntsmen and Huntresses to battle the evils of the world, and Ruby, Weiss, Blake, and Yang are ready for their first day of class.",
    "alias": [
      "RWBY Volume 9",
      "红白黑黄 第九季"
    ],
    "tags": [
      "2023年1月",
      "3D",
      "RWBY",
      "WEB",
      "原创",
      "奇幻",
      "战斗",
      "欧美",
      "百合"
    ],
    "search": {
      "include": [
        "RWBY Volume 9",
        "红白黑黄 第九季"
      ]
    }
  },
  {
    "id": 409323,
    "title": "开阔天空！光之美少女",
    "platform": "TV",
    "onair_date": "2023-02-05",
    "rating": {
      "score": 5.7,
      "rank": 8158
    },
    "poster": "https://lain.bgm.tv/pic/cover/l/38/8e/409323_8axt1.jpg",
    "images": [
      {
        "provider": "bgm",
        "quality": "large",
        "src": "https://lain.bgm.tv/pic/cover/l/38/8e/409323_8axt1.jpg"
      },
      {
        "provider": "bgm",
        "quality": "common",
        "src": "https://lain.bgm.tv/r/400/pic/cover/l/38/8e/409323_8axt1.jpg"
      },
      {
        "provider": "bgm",
        "quality": "medium",
        "src": "https://lain.bgm.tv/r/800/pic/cover/l/38/8e/409323_8axt1.jpg"
      },
      {
        "provider": "bgm",
        "quality": "small",
        "src": "https://lain.bgm.tv/r/200/pic/cover/l/38/8e/409323_8axt1.jpg"
      },
      {
        "provider": "bgm",
        "quality": "grid",
        "src": "https://lain.bgm.tv/r/100/pic/cover/l/38/8e/409323_8axt1.jpg"
      }
    ],
    "summary": "和平的天空之地发生了大事件！？年幼的艾尔公主被安达古帝国给带走了！勇敢的少女索拉追着公主来到不可思议的洞穴，洞穴居然是通往异世界的天窗市！？电视？车子！？是魔法道具吗…！？没时间感到惊讶！要快点将公主带回…！飞往两个不同世界！光之美少女们的冒险即将开始了！英雄在此登场！",
    "alias": [
      "Expanding Sky! Precure",
      "Hirogaru Sky! Precure",
      "Soaring Sky! Pretty Cure",
      "ひろがるスカイ！プリキュア",
      "ひろプリ",
      "伸向天空！光之美少女",
      "天空Q娃",
      "开阔天空！光之美少女",
      "海阔天空！光之美少女",
      "空Q"
    ],
    "tags": [
      "2023年2月",
      "TV",
      "プリキュア",
      "东映",
      "东映アニメーション",
      "光之美少女",
      "原创",
      "小川孝治",
      "年番",
      "战斗",
      "百合",
      "金月龙之介"
    ],
    "search": {
      "include": [
        "Expanding Sky! Precure",
        "Hirogaru Sky! Precure",
        "Soaring Sky! Pretty Cure",
        "ひろがるスカイ！プリキュア",
        "ひろプリ",
        "伸向天空！光之美少女",
        "天空Q娃",
        "开阔天空！光之美少女",
        "海阔天空！光之美少女",
        "空Q"
      ]
    }
  },
  {
    "id": 419847,
    "title": "辣糖甜心",
    "platform": "WEB",
    "onair_date": "2023-02-14",
    "rating": {
      "score": 5.5,
      "rank": 0
    },
    "poster": "https://lain.bgm.tv/pic/cover/l/b7/94/419847_1LlzK.jpg",
    "images": [
      {
        "provider": "bgm",
        "quality": "large",
        "src": "https://lain.bgm.tv/pic/cover/l/b7/94/419847_1LlzK.jpg"
      },
      {
        "provider": "bgm",
        "quality": "common",
        "src": "https://lain.bgm.tv/r/400/pic/cover/l/b7/94/419847_1LlzK.jpg"
      },
      {
        "provider": "bgm",
        "quality": "medium",
        "src": "https://lain.bgm.tv/r/800/pic/cover/l/b7/94/419847_1LlzK.jpg"
      },
      {
        "provider": "bgm",
        "quality": "small",
        "src": "https://lain.bgm.tv/r/200/pic/cover/l/b7/94/419847_1LlzK.jpg"
      },
      {
        "provider": "bgm",
        "quality": "grid",
        "src": "https://lain.bgm.tv/r/100/pic/cover/l/b7/94/419847_1LlzK.jpg"
      }
    ],
    "summary": "ツッコミ系毒舌女子の Spicy が、\n日常の些細な「あるある」「ぼやき」「これって変じゃない？」を\nメロディーに乗せて歌い出します。",
    "alias": [
      "Spicy Candy",
      "スパイシーキャンディ",
      "辣糖甜心"
    ],
    "tags": [
      "2023",
      "泡面番"
    ],
    "search": {
      "include": [
        "Spicy Candy",
        "スパイシーキャンディ",
        "辣糖甜心"
      ]
    }
  },
  {
    "id": 420442,
    "title": "KUROMI'S PRETTY JOURNEY",
    "platform": "WEB",
    "onair_date": "2023-02-17",
    "rating": {
      "score": 6.4,
      "rank": 0
    },
    "poster": "https://lain.bgm.tv/pic/cover/l/69/28/420442_KkK3C.jpg",
    "images": [
      {
        "provider": "bgm",
        "quality": "large",
        "src": "https://lain.bgm.tv/pic/cover/l/69/28/420442_KkK3C.jpg"
      },
      {
        "provider": "bgm",
        "quality": "common",
        "src": "https://lain.bgm.tv/r/400/pic/cover/l/69/28/420442_KkK3C.jpg"
      },
      {
        "provider": "bgm",
        "quality": "medium",
        "src": "https://lain.bgm.tv/r/800/pic/cover/l/69/28/420442_KkK3C.jpg"
      },
      {
        "provider": "bgm",
        "quality": "small",
        "src": "https://lain.bgm.tv/r/200/pic/cover/l/69/28/420442_KkK3C.jpg"
      },
      {
        "provider": "bgm",
        "quality": "grid",
        "src": "https://lain.bgm.tv/r/100/pic/cover/l/69/28/420442_KkK3C.jpg"
      }
    ],
    "summary": "笑いあり涙ありなんでもありの\nクロミと仲間たちによるドキドキ大冒険が\nついにスタート！世界を股にかけて活躍\nするクロミを応援してね！",
    "alias": [
      "KUROMI'S PRETTY JOURNEY",
      "クロミズ・プリティ・ジャーニー"
    ],
    "tags": [
      "2023年4月",
      "WEB",
      "泡面番"
    ],
    "search": {
      "include": [
        "KUROMI'S PRETTY JOURNEY",
        "クロミズ・プリティ・ジャーニー"
      ]
    }
  }
]