[
  {
    "id": 83545,
    "title": "长靴猫环游世界八十天",
    "data": {
      "id": 83545,
      "title": "长靴猫环游世界八十天",
      "platform": "剧场版",
      "onair_date": "1976-03-20",
      "alias": [
        "Puss in Boots: Travels Around the World in 80 Days",
        "穿长靴的猫 80日环游世界",
        "長靴をはいた猫 80日間世界一周",
        "长靴猫环游世界八十天"
      ],
      "rating": {
        "score": 5.8,
        "rank": 0
      },
      "summary": "ある街でレストランの給仕をしていたペロは、横柄な客グルーモン卿と口論になり、「八十日間で世界を一周してみせる。できなかったらグルーモンの奴隷になる」という賭けをする。 ペロはネズミの父子やレストランのコックのカーターとともに、時間に追われながら苦難の旅を続けるが、グルーモン卿の手先のガリガリ博士、そして謎の美女スザンナが妨害してくる。",
      "poster": "https://lain.bgm.tv/pic/cover/l/f1/96/83545_JqLJI.jpg",
      "images": [
        {
          "provider": "bgm",
          "quality": "large",
          "src": "https://lain.bgm.tv/pic/cover/l/f1/96/83545_JqLJI.jpg"
        },
        {
          "provider": "bgm",
          "quality": "common",
          "src": "https://lain.bgm.tv/r/400/pic/cover/l/f1/96/83545_JqLJI.jpg"
        },
        {
          "provider": "bgm",
          "quality": "medium",
          "src": "https://lain.bgm.tv/r/800/pic/cover/l/f1/96/83545_JqLJI.jpg"
        },
        {
          "provider": "bgm",
          "quality": "small",
          "src": "https://lain.bgm.tv/r/200/pic/cover/l/f1/96/83545_JqLJI.jpg"
        },
        {
          "provider": "bgm",
          "quality": "grid",
          "src": "https://lain.bgm.tv/r/100/pic/cover/l/f1/96/83545_JqLJI.jpg"
        }
      ],
      "tags": [
        "剧场版"
      ]
    },
    "search": {
      "include": [
        "Puss in Boots: Travels Around the World in 80 Days",
        "穿长靴的猫 80日环游世界",
        "長靴をはいた猫 80日間世界一周",
        "长靴猫环游世界八十天"
      ]
    },
    "updatedAt": "2025-10-18T10:22:28.493Z"
  },
  {
    "id": 112964,
    "title": "UFO机器人古连泰沙对大魔神",
    "data": {
      "id": 112964,
      "title": "UFO机器人古连泰沙对大魔神",
      "platform": "剧场版",
      "onair_date": "1976-03-20",
      "alias": [
        "UFO Robo Grandizer Vs. Great Mazinger",
        "UFOロボ グレンダイザー対グレートマジンガー",
        "UFO机器人古连泰沙对大魔神",
        "铁甲万能侠之决战巨灵神"
      ],
      "rating": {
        "score": 5.7,
        "rank": 0
      },
      "summary": "永井豪原作のヒーローが競演するマジンガーシリーズ劇場オリジナル作品第５弾。今回は、グレートマジンガーが敵の手に落ち、タイトル通りの２大ロボットの対決を堪能できる。グレンダイザーを倒すため、ベガ星連合軍のバレンドス親衛隊長が地球へと送りこまれてきた。宇宙科学研究所の兜甲児は、単身、バレンドスに立ち向かうが、円盤獣ジンジンによって捕らわれてしまう。甲児を脳波探知機にかけ、グレートマジンガーの存在を知ったバレンドスは、ロボット博物館を急襲。グレートマジンガーを奪取するのだった。",
      "poster": "https://lain.bgm.tv/pic/cover/l/e1/d9/112964_aU5E9.jpg",
      "images": [
        {
          "provider": "bgm",
          "quality": "large",
          "src": "https://lain.bgm.tv/pic/cover/l/e1/d9/112964_aU5E9.jpg"
        },
        {
          "provider": "bgm",
          "quality": "common",
          "src": "https://lain.bgm.tv/r/400/pic/cover/l/e1/d9/112964_aU5E9.jpg"
        },
        {
          "provider": "bgm",
          "quality": "medium",
          "src": "https://lain.bgm.tv/r/800/pic/cover/l/e1/d9/112964_aU5E9.jpg"
        },
        {
          "provider": "bgm",
          "quality": "small",
          "src": "https://lain.bgm.tv/r/200/pic/cover/l/e1/d9/112964_aU5E9.jpg"
        },
        {
          "provider": "bgm",
          "quality": "grid",
          "src": "https://lain.bgm.tv/r/100/pic/cover/l/e1/d9/112964_aU5E9.jpg"
        }
      ],
      "tags": [
        "1976",
        "剧场版",
        "萝卜"
      ]
    },
    "search": {
      "include": [
        "UFO Robo Grandizer Vs. Great Mazinger",
        "UFOロボ グレンダイザー対グレートマジンガー",
        "UFO机器人古连泰沙对大魔神",
        "铁甲万能侠之决战巨灵神"
      ]
    },
    "updatedAt": "2025-10-18T10:26:44.755Z"
  }
]