[
  {
    "id": 88595,
    "title": "蜘蛛与郁金香",
    "platform": "剧场版",
    "onair_date": "1943-04-15",
    "rating": {
      "score": 6.6,
      "rank": 3483
    },
    "poster": "https://lain.bgm.tv/pic/cover/l/4f/af/88595_hIgpR.jpg",
    "images": [
      {
        "provider": "bgm",
        "quality": "large",
        "src": "https://lain.bgm.tv/pic/cover/l/4f/af/88595_hIgpR.jpg"
      },
      {
        "provider": "bgm",
        "quality": "common",
        "src": "https://lain.bgm.tv/r/400/pic/cover/l/4f/af/88595_hIgpR.jpg"
      },
      {
        "provider": "bgm",
        "quality": "medium",
        "src": "https://lain.bgm.tv/r/800/pic/cover/l/4f/af/88595_hIgpR.jpg"
      },
      {
        "provider": "bgm",
        "quality": "small",
        "src": "https://lain.bgm.tv/r/200/pic/cover/l/4f/af/88595_hIgpR.jpg"
      },
      {
        "provider": "bgm",
        "quality": "grid",
        "src": "https://lain.bgm.tv/r/100/pic/cover/l/4f/af/88595_hIgpR.jpg"
      }
    ],
    "summary": "花畑を舞台とし、てんとう虫の女の子とクモとの追い掛けっこが物語の軸となっている。\n樹の上にクモの巣を張り、その前にあるハンモックへ誰かを乗せようと辺りを見回したクモは、歌を歌う女の子を見つけ「ハンモックへ乗って遊ばないか」と誘う。てんとう虫の女の子は「ありがとう」としながらも「陽が落ちて、三日月さまが出たから遊ばない」と断りクモと別れる。諦めきれないクモは糸を巧みに操りながら執拗にてんとう虫を追いかけ続け、危険を察したチューリップは花の中にてんとう虫を引き入れてかくまう。そのことを知ったクモはチューリップを大量の糸でグルグル巻きにして、てんとう虫が外へ出られないようにしたうえでハンモックへ戻り、眠ってしまう。しばらくすると大粒の雨が降り出し、やがて雷鳴と強風の嵐へと変わり、ハンモックは風で飛ばされ、クモの巣も半分が失われた。糸を掴んで飛ばされずに済んでいたクモも巣を修復している最中に飛んできた枝に当たって遠くへ飛ばされ、別の樹へたどり着く。そこでミノムシの子供から蓑を奪い取って嵐が通り過ぎるのを待とうとするクモであったが、身に付けた際に足が蓑の中に隠れて身動きが取れなくなったうえ糸を操ることもできなくなり、遠くへ飛ばされて水の中へ没する。\n嵐が過ぎ去り太陽の陽が輝く花畑では、チューリップの中にいたため難を逃れたてんとう虫が外へ出て、再び歌い始める。樹の上にクモの姿はなく、陽に照らされて雨露が輝く半分のクモの巣だけが残されていた。",
    "alias": [
      "Kumo to Chūrippu",
      "Kumo to Tulip",
      "くもとちゅうりっぷ",
      "クモとチューリップ",
      "蜘蛛与郁金香"
    ],
    "tags": [
      "1943",
      "原创",
      "政冈宪三",
      "松竹映画",
      "横山美智子",
      "短片"
    ],
    "search": {
      "include": [
        "Kumo to Chūrippu",
        "Kumo to Tulip",
        "くもとちゅうりっぷ",
        "クモとチューリップ",
        "蜘蛛与郁金香"
      ]
    }
  }
]